Workbook

Sheet composit
A1: MKT | B1: yearq | C1: COMP | D1: R | E1: STK | F1: CAP | G1: CPI | H1: T10
A2: Atlanta | B2: 1987.1 | C2: 3993 | D2: 13.41 | E2: 58838 | F2: 7.289683 | G2: 111.8 | H2: 7.1954098
A3: Atlanta | B3: 1987.2 | C3: 949 | D3: 13.34 | E3: 59787 | F3: 7.248712 | G3: 113.06667 | H3: 8.3426984
A4: Atlanta | B4: 1987.3 | C4: 1637 | D4: 13.36 | E4: 61424 | F4: 6.61851 | G4: 114.26667 | H4: 8.8696875
A5: Atlanta | B5: 1987.4 | C5: 2055 | D5: 13.38 | E5: 63479 | F5: 6.505085 | G5: 115.33333 | H5: 9.1290323
A6: Atlanta | B6: 1988.1 | C6: 225 | D6: 13.55 | E6: 63704 | F6: 6.567542 | G6: 116.23333 | H6: 8.4109677
A7: Atlanta | B7: 1988.2 | C7: 916 | D7: 13.72 | E7: 64620 | F7: 6.677471 | G7: 117.56667 | H7: 8.9128571
A8: Atlanta | B8: 1988.3 | C8: 229 | D8: 13.83 | E8: 64849 | F8: 7.509844 | G8: 119 | H8: 9.1035938
A9: Atlanta | B9: 1988.4 | C9: 1157 | D9: 13.95 | E9: 66006 | F9: 7.625062 | G9: 120.3 | H9: 8.9570492
A10: Atlanta | B10: 1989.1 | C10: 1786 | D10: 13.61 | E10: 67792 | F10: 7.7636 | G10: 121.66667 | H10: 9.2116393
A11: Atlanta | B11: 1989.2 | C11: 1553 | D11: 13.27 | E11: 69345 | F11: 8.055134 | G11: 123.63333 | H11: 8.7579688
A12: Atlanta | B12: 1989.3 | C12: 1973 | D12: 13.2 | E12: 71318 | F12: 7.491521 | G12: 124.6 | H12: 8.1074603
A13: Atlanta | B13: 1989.4 | C13: 1227 | D13: 13.13 | E13: 72545 | F13: 7.215834 | G13: 125.86667 | H13: 7.9070968
... A549: NewYork | B549: 2000.4 | C549: 0 | D549: 51.51 | E549: 464247 | F549: 6.993196 | G549: 174.23333 | H549: 5.5706452
A550: NewYork | B550: 2001.1 | C550: 2754 | D550: 55.96 | E550: =E549+C550 -> 467001 | F550: 7.417615 | G550: 175.9 | H550: 5.0441935
A551: NewYork | B551: 2001.2 | C551: 287 | D551: 57.25 | E551: =E550+C551 -> 467288 | F551: 7.725923 | G551: 177.13333 | H551: 5.2761905
A552: NewYork | B552: 2001.3 | C552: 0 | D552: 55.31 | E552: =E551+C552 -> 467288 | F552: 7.927756 | G552: 177.63333 | H552: 4.9957377
A553: NewYork | B553: 2001.4 | C553: 78 | D553: 55.59 | E553: =E552+C553 -> 467366 | F553: 8.121367 | G553: 177.5 | H553: 4.7620968
A554: NewYork | B554: 2002.1 | C554: 8024 | D554: 56.11 | E554: =E553+C554 -> 475390 | F554: 8.209994 | G554: 178.06667 | H554: 5.0791667
A555: NewYork | B555: 2002.2 | C555: 3407 | D555: 54.92 | E555: =E554+C555 -> 478797 | F555: 8.280957 | G555: 179.46667 | H555: 5.1060937
A556: NewYork | B556: 2002.3 | C556: 550 | D556: 54.86 | E556: =E555+C556 -> 479347 | F556: 8.380952 | G556: 180.43333 | H556: 4.2723437
A557: NewYork | B557: 2002.4 | C557: 173 | D557: 53.92 | E557: =E556+C557 -> 479520 | F557: 8.448381 | G557: 181.5 | H557: 4.0048387
A558: NewYork | B558: 2003.1 | C558: 788 | D558: 52.61 | E558: =E557+C558 -> 480308 | F558: 8.331318 | G558: 183.36667 | H558: 3.92
A559: NewYork | B559: 2003.2 | C559: 570 | D559: 50.77 | E559: =E558+C559 -> 480878 | F559: 8.306798 | G559: 183.06667 | H559: 3.6206349
A560: NewYork | B560: 2003.3 | C560: 1339 | D560: 48.13 | E560: =E559+C560 -> 482217 | F560: 7.941854 | G560: 184.43333 | H560: 4.2276562
A561: NewYork | B561: 2003.4 | C561: 1407 | D561: 45.68 | E561: =E560+C561 -> 483624 | F561: 7.848067 | G561: 185.13333 | H561: 4.2851613
... A616: NewYork | B616: 2017.3 | C616: 86 | D616: 68.65 | E616: =E615+C616 -> 509805 | F616: 3.695916 | G616: 245.287 | H616: 2.241429
A617: OrangeCounty | B617: 1987.1 | C617: 304 | D617: 19.68 | E617: 34721 | F617: 7.969785 | G617: 111.8 | H617: 7.1954098
A618: OrangeCounty | B618: 1987.2 | C618: 592 | D618: 19.17 | E618: 35313 | F618: 8.066318 | G618: 113.06667 | H618: 8.3426984
A619: OrangeCounty | B619: 1987.3 | C619: 882 | D619: 18.91 | E619: 36195 | F619: 8.123709 | G619: 114.26667 | H619: 8.8696875
A620: OrangeCounty | B620: 1987.4 | C620: 4010 | D620: 18.66 | E620: 40205 | F620: 8.084139 | G620: 115.33333 | H620: 9.1290323
A621: OrangeCounty | B621: 1988.1 | C621: 1233 | D621: 18.79 | E621: 41438 | F621: 8.018904 | G621: 116.23333 | H621: 8.4109677
A622: OrangeCounty | B622: 1988.2 | C622: 1008 | D622: 18.91 | E622: 42446 | F622: 8.038604 | G622: 117.56667 | H622: 8.9128571
A623: OrangeCounty | B623: 1988.3 | C623: 726 | D623: 18.8 | E623: 43172 | F623: 7.857322 | G623: 119 | H623: 9.1035938
A624: OrangeCounty | B624: 1988.4 | C624: 172 | D624: 18.68 | E624: 43344 | F624: 7.572741 | G624: 120.3 | H624: 8.9570492
A625: OrangeCounty | B625: 1989.1 | C625: 1905 | D625: 18.53 | E625: 45249 | F625: 7.52181 | G625: 121.66667 | H625: 9.2116393
A626: OrangeCounty | B626: 1989.2 | C626: 664 | D626: 18.38 | E626: 45913 | F626: 7.267149 | G626: 123.63333 | H626: 8.7579688
A627: OrangeCounty | B627: 1989.3 | C627: 841 | D627: 18.21 | E627: 46754 | F627: 7.065044 | G627: 124.6 | H627: 8.1074603
A628: OrangeCounty | B628: 1989.4 | C628: 835 | D628: 18.05 | E628: 47589 | F628: 7.049333 | G628: 125.86667 | H628: 7.9070968
... A985: SanJose | B985: 2017.3 | C985: 1126 | D985: 36.5 | E985: 49002 | F985: 4.731175 | G985: 245.287 | H985: 2.241429

Sheet Model 1 ATL
A1: SUMMARY OUTPUT
A3: Regression Statistics
A4: Multiple R | B4: 0.72177316
A5: R Square | B5: 0.5209565
A6: Adjusted R Square | B6: 0.50845971
A7: Standard Error | B7: 0.96119497
A8: Observations | B8: 119
A10: ANOVA
B11: df | C11: SS | D11: MS | E11: F | F11: Significance F
A12: Regression | B12: 3 | C12: 115.54398 | D12: 38.51466 | E12: 41.687235 | F12: 2.6208358e-18
A13: Residual | B13: 115 | C13: 106.24801 | D13: 0.92389576
A14: Total | B14: 118 | C14: 221.79199
B16: Coefficients | C16: Standard Error | D16: t Stat | E16: P-value | F16: Lower 95% | G16: Upper 95% | H16: Lower 95.0% | I16: Upper 95.0%
A17: Intercept | B17: 3.5751792 | C17: 1.9382698 | D17: 1.8445209 | E17: 0.067680789 | F17: -0.26416023 | G17: 7.4145187 | H17: -0.26416023 | I17: 7.4145187
A18: X Variable 1 | B18: 0.71464442 | C18: 0.069718823 | D18: 10.25038 | E18: 6.6078277e-18 | F18: 0.57654485 | G18: 0.85274399 | H18: 0.57654485 | I18: 0.85274399
A19: X Variable 2 | B19: 0.074887428 | C19: 0.043495189 | D19: 1.7217405 | E19: 0.087805294 | F19: -0.011268171 | G19: 0.16104303 | H19: -0.011268171 | I19: 0.16104303
A20: X Variable 3 | B20: -1.9126115 | C20: 1.863509 | D20: -1.0263495 | E20: 0.30688088 | F20: -5.6038641 | G20: 1.7786411 | H20: -5.6038641 | I20: 1.7786411
A24: RESIDUAL OUTPUT
A26: Observation | B26: Predicted Y | C26: Residuals
A27: 1 | B27: 7.4820072 | C27: -0.91446519
A28: 2 | B28: 7.4557981 | C28: -0.77832712
A29: 3 | B29: 7.0069087 | C29: 0.50293525
A30: 4 | B30: 6.9006819 | C30: 0.72438012
A31: 5 | B31: 7.0373919 | C31: 0.72620814
A32: 6 | B32: 7.1531783 | C32: 0.90195566
A33: 7 | B33: 7.7237082 | C33: -0.2321872
A34: 8 | B34: 7.8163438 | C34: -0.60050983
A35: 9 | B35: 7.9315623 | C35: -1.0704903
A36: 10 | B36: 8.1350074 | C36: -2.0266874
A37: 11 | B37: 7.7114256 | C37: -1.9760946
A38: 12 | B38: 7.4706747 | C38: -2.3588497
... A145: 119 | B145: 5.439303 | C145: -0.291107

Sheet Model 2 ATL
A1: SUMMARY OUTPUT
A3: Regression Statistics
A4: Multiple R | B4: 0.78313953
A5: R Square | B5: 0.61330753
A6: Adjusted R Square | B6: 0.59973937
A7: Standard Error | B7: 0.86736794
A8: Observations | B8: 119
A10: ANOVA
B11: df | C11: SS | D11: MS | E11: F | F11: Significance F
A12: Regression | B12: 4 | C12: 136.0267 | D12: 34.006675 | E12: 45.201978 | F12: 1.0855447e-22
A13: Residual | B13: 114 | C13: 85.765294 | D13: 0.75232714
A14: Total | B14: 118 | C14: 221.79199
B16: Coefficients | C16: Standard Error | D16: t Stat | E16: P-value | F16: Lower 95% | G16: Upper 95% | H16: Lower 95.0% | I16: Upper 95.0%
A17: Intercept | B17: 47.123533 | C17: 8.5273609 | D17: 5.5261567 | E17: 2.0971044e-07 | F17: 30.230897 | G17: 64.016169 | H17: 30.230897 | I17: 64.016169
A18: X Variable 1 | B18: 0.68744746 | C18: 0.063128769 | D18: 10.889607 | E18: 2.3113174e-19 | F18: 0.56238985 | G18: 0.81250507 | H18: 0.56238985 | I18: 0.81250507
A19: X Variable 2 | B19: 0.25341247 | C19: 0.052068607 | D19: 4.8668954 | E19: 3.6727759e-06 | F19: 0.15026496 | G19: 0.35655998 | H19: 0.15026496 | I19: 0.35655998
A20: X Variable 3 | B20: -3.0632231 | C20: 1.6959994 | D20: -1.8061463 | E20: 0.07353392 | F20: -6.4229849 | G20: 0.29653875 | H20: -6.4229849 | I20: 0.29653875
A21: X Variable 4 | B21: -41.969148 | C21: 8.0434009 | D21: -5.2178362 | E21: 8.2033629e-07 | F21: -57.903063 | G21: -26.035233 | H21: -57.903063 | I21: -26.035233
A25: RESIDUAL OUTPUT
A27: Observation | B27: Predicted Y | C27: Residuals
A28: 1 | B28: 7.5376494 | C28: -0.97010736
A29: 2 | B29: 7.5752891 | C29: -0.89781807
A30: 3 | B30: 7.1017288 | C30: 0.40811519
A31: 4 | B31: 6.8950559 | C31: 0.73000606
A32: 5 | B32: 6.964932 | C32: 0.798668
A33: 6 | B33: 6.835732 | C33: 1.219402
A34: 7 | B34: 7.4728372 | C34: 0.018683755
A35: 8 | B35: 7.5747616 | C35: -0.35892763
A36: 9 | B36: 7.5107948 | C36: -0.64972283
A37: 10 | B37: 8.0093276 | C37: -1.9010076
A38: 11 | B38: 7.180456 | C38: -1.445125
A39: 12 | B39: 6.5826541 | C39: -1.4708291
... A146: 119 | B146: 5.2590963 | C146: -0.11090031

Sheet Atlanta
A1: MKT | B1: yearq | C1: COMP | D1: R | E1: STK | F1: CAP | G1: CPI | H1: T10 | L1: CAP | M1: CAP(t-4) | N1: T10 | O1: Rt/Rt-4 | P1: CPIt/CPI(t-4)
A2: Atlanta | B2: 1987.1 | C2: 3993 | D2: 13.41 | E2: 58838 | F2: 7.289683 | G2: 111.8 | H2: 7.1954098 | L2: 7.289683 | N2: 7.1954098
A3: Atlanta | B3: 1987.2 | C3: 949 | D3: 13.34 | E3: 59787 | F3: 7.248712 | G3: 113.06667 | H3: 8.3426984 | L3: 7.248712 | N3: 8.3426984
A4: Atlanta | B4: 1987.3 | C4: 1637 | D4: 13.36 | E4: 61424 | F4: 6.61851 | G4: 114.26667 | H4: 8.8696875 | L4: 6.61851 | N4: 8.8696875
A5: Atlanta | B5: 1987.4 | C5: 2055 | D5: 13.38 | E5: 63479 | F5: 6.505085 | G5: 115.33333 | H5: 9.1290323 | L5: 6.505085 | N5: 9.1290323
A6: Atlanta | B6: 1988.1 | C6: 225 | D6: 13.55 | E6: 63704 | F6: 6.567542 | G6: 116.23333 | H6: 8.4109677 | L6: 6.567542 | M6: =F2 -> 7.289683 | N6: 8.4109677 | O6: =D6/D2 -> 1.01044 | P6: =G6/G2 -> 1.0396541
A7: Atlanta | B7: 1988.2 | C7: 916 | D7: 13.72 | E7: 64620 | F7: 6.677471 | G7: 117.56667 | H7: 8.9128571 | L7: 6.677471 | M7: =F3 -> 7.248712 | N7: 8.9128571 | O7: =D7/D3 -> 1.0284858 | P7: =G7/G3 -> 1.0397995
A8: Atlanta | B8: 1988.3 | C8: 229 | D8: 13.83 | E8: 64849 | F8: 7.509844 | G8: 119 | H8: 9.1035937 | L8: 7.509844 | M8: =F4 -> 6.61851 | N8: 9.1035937 | O8: =D8/D4 -> 1.0351796 | P8: =G8/G4 -> 1.0414236
A9: Atlanta | B9: 1988.4 | C9: 1157 | D9: 13.95 | E9: 66006 | F9: 7.625062 | G9: 120.3 | H9: 8.9570492 | L9: 7.625062 | M9: =F5 -> 6.505085 | N9: 8.9570492 | O9: =D9/D5 -> 1.0426009 | P9: =G9/G5 -> 1.0430636
A10: Atlanta | B10: 1989.1 | C10: 1786 | D10: 13.61 | E10: 67792 | F10: 7.7636 | G10: 121.66667 | H10: 9.2116393 | L10: 7.7636 | M10: =F6 -> 6.567542 | N10: 9.2116393 | O10: =D10/D6 -> 1.004428 | P10: =G10/G6 -> 1.0467451
A11: Atlanta | B11: 1989.2 | C11: 1553 | D11: 13.27 | E11: 69345 | F11: 8.055134 | G11: 123.63333 | H11: 8.7579687 | L11: 8.055134 | M11: =F7 -> 6.677471 | N11: 8.7579687 | O11: =D11/D7 -> 0.96720117 | P11: =G11/G7 -> 1.0516019
A12: Atlanta | B12: 1989.3 | C12: 1973 | D12: 13.2 | E12: 71318 | F12: 7.491521 | G12: 124.6 | H12: 8.1074603 | L12: 7.491521 | M12: =F8 -> 7.509844 | N12: 8.1074603 | O12: =D12/D8 -> 0.95444685 | P12: =G12/G8 -> 1.0470588
A13: Atlanta | B13: 1989.4 | C13: 1227 | D13: 13.13 | E13: 72545 | F13: 7.215834 | G13: 125.86667 | H13: 7.9070968 | L13: 7.215834 | M13: =F9 -> 7.625062 | N13: 7.9070968 | O13: =D13/D9 -> 0.94121864 | P13: =G13/G9 -> 1.0462732
A14: Atlanta | B14: 1990.1 | C14: 162 | D14: 12.97 | E14: 72707 | F14: 6.861072 | G14: 128.03333 | H14: 8.423871 | L14: 6.861072 | M14: =F10 -> 7.7636 | N14: 8.423871 | O14: =D14/D10 -> 0.95297575 | P14: =G14/G10 -> 1.0523288
A15: Atlanta | B15: 1990.2 | C15: 161 | D15: 12.81 | E15: 72868 | F15: 6.10832 | G15: 129.3 | H15: 8.674127 | L15: 6.10832 | M15: =F11 -> 8.055134 | N15: 8.674127 | O15: =D15/D11 -> 0.96533534 | P15: =G15/G11 -> 1.0458345
A16: Atlanta | B16: 1990.3 | C16: 940 | D16: 12.9 | E16: 73808 | F16: 5.735331 | G16: 131.53333 | H16: 8.7012698 | L16: 5.735331 | M16: =F12 -> 7.491521 | N16: 8.7012698 | O16: =D16/D12 -> 0.97727273 | P16: =G16/G12 -> 1.0556447
A17: Atlanta | B17: 1990.4 | C17: 1027 | D17: 12.98 | E17: 74835 | F17: 5.111825 | G17: 133.76667 | H17: 8.4059677 | L17: 5.111825 | M17: =F13 -> 7.215834 | N17: 8.4059677 | O17: =D17/D13 -> 0.98857578 | P17: =G17/G13 -> 1.0627648
... A124: Atlanta | B124: 2017.3 | C124: 231 | D124: 21.26 | E124: 141452 | F124: 5.148196 | G124: 245.287 | H124: 2.241429 | L124: 5.148196 | M124: =F120 -> 5.170949 | N124: 2.241429 | O124: =D124/D120 -> 1.0452311 | P124: =G124/G120 -> 1.0194494

Sheet Model1 Bos
A1: SUMMARY OUTPUT
A3: Regression Statistics
A4: Multiple R | B4: 0.85347147
A5: R Square | B5: 0.72841355
A6: Adjusted R Square | B6: 0.72132869
A7: Standard Error | B7: 0.91712387
A8: Observations | B8: 119
A10: ANOVA
B11: df | C11: SS | D11: MS | E11: F | F11: Significance F
A12: Regression | B12: 3 | C12: 259.43213 | D12: 86.477377 | E12: 102.81264 | F12: 2.076763e-32
A13: Residual | B13: 115 | C13: 96.728363 | D13: 0.8411162
A14: Total | B14: 118 | C14: 356.16049
B16: Coefficients | C16: Standard Error | D16: t Stat | E16: P-value | F16: Lower 95% | G16: Upper 95% | H16: Lower 95.0% | I16: Upper 95.0%
A17: Intercept | B17: 2.9797851 | C17: 0.8431311 | D17: 3.5341896 | E17: 0.00059020637 | F17: 1.3097047 | G17: 4.6498656 | H17: 1.3097047 | I17: 4.6498656
A18: X Variable 1 | B18: 0.84455618 | C18: 0.059643654 | D18: 14.160034 | E18: 5.8093207e-27 | F18: 0.72641358 | G18: 0.96269878 | H18: 0.72641358 | I18: 0.96269878
A19: X Variable 2 | B19: 0.067168611 | C19: 0.046723462 | D19: 1.4375778 | E19: 0.15326938 | F19: -0.025381575 | G19: 0.1597188 | H19: -0.025381575 | I19: 0.1597188
A20: X Variable 3 | B20: -2.2963517 | C20: 0.75226436 | D20: -3.052586 | E20: 0.0028185317 | F20: -3.7864426 | G20: -0.80626075 | H20: -3.7864426 | I20: -0.80626075
A24: RESIDUAL OUTPUT
A26: Observation | B26: Predicted Y | C26: Residuals
A27: 1 | B27: 7.60459 | C27: -0.57270399
A28: 2 | B28: 7.5742394 | C28: -0.8656964
A29: 3 | B29: 7.6192021 | C29: -0.92250612
A30: 4 | B30: 7.2193709 | C30: -0.4880349
A31: 5 | B31: 7.2730721 | C31: -0.54247109
A32: 6 | B32: 7.0443546 | C32: -0.12455858
A33: 7 | B33: 6.993453 | C33: -0.19886704
A34: 8 | B34: 7.0120433 | C34: -0.35073129
A35: 9 | B35: 7.0647594 | C35: -0.73713844
A36: 10 | B36: 7.2597395 | C36: -1.2790375
A37: 11 | B37: 7.1760959 | C37: -1.2333199
A38: 12 | B38: 7.0650127 | C38: -1.0773267
... A145: 119 | B145: 4.0466471 | C145: -0.16751609

Sheet Model 2 Bos
A1: SUMMARY OUTPUT
A3: Regression Statistics
A4: Multiple R | B4: 0.87725777
A5: R Square | B5: 0.76958119
A6: Adjusted R Square | B6: 0.76149632
A7: Standard Error | B7: 0.84845617
A8: Observations | B8: 119
A10: ANOVA
B11: df | C11: SS | D11: MS | E11: F | F11: Significance F
A12: Regression | B12: 4 | C12: 274.09442 | D12: 68.523604 | E12: 95.187819 | F12: 2.0674761e-35
A13: Residual | B13: 114 | C13: 82.066077 | D13: 0.71987786
A14: Total | B14: 118 | C14: 356.16049
B16: Coefficients | C16: Standard Error | D16: t Stat | E16: P-value | F16: Lower 95% | G16: Upper 95% | H16: Lower 95.0% | I16: Upper 95.0%
A17: Intercept | B17: 38.284174 | C17: 7.8615016 | D17: 4.8698298 | E17: 3.6279364e-06 | F17: 22.7106 | G17: 53.857748 | H17: 22.7106 | I17: 53.857748
A18: X Variable 1 | B18: 0.82652172 | C18: 0.055322472 | D18: 14.940072 | E18: 1.2995747e-28 | F18: 0.71692833 | G18: 0.93611511 | H18: 0.71692833 | I18: 0.93611511
A19: X Variable 2 | B19: 0.2208476 | C19: 0.055026847 | D19: 4.0134518 | E19: 0.00010742096 | F19: 0.11183984 | G19: 0.32985536 | H19: 0.11183984 | I19: 0.32985536
A20: X Variable 3 | B20: -2.088515 | C20: 0.6974622 | D20: -2.994449 | E20: 0.0033726989 | F20: -3.4701822 | G20: -0.70684774 | H20: -3.4701822 | I20: -0.70684774
A21: X Variable 4 | B21: -35.230574 | C21: 7.8063547 | D21: -4.5130634 | E21: 1.563359e-05 | F21: -50.694903 | G21: -19.766245 | H21: -50.694903 | I21: -19.766245
A25: RESIDUAL OUTPUT
A27: Observation | B27: Predicted Y | C27: Residuals
A28: 1 | B28: 7.6486601 | C28: -0.61677412
A29: 2 | B29: 7.6956795 | C29: -0.9871365
A30: 3 | B30: 7.7103316 | C30: -1.0136356
A31: 4 | B31: 7.2369158 | C31: -0.50557978
A32: 5 | B32: 7.1937842 | C32: -0.46318319
A33: 6 | B33: 6.7232946 | C33: 0.19650136
A34: 7 | B34: 6.7324402 | C34: 0.062145763
A35: 8 | B35: 6.7470391 | C35: -0.085727092
A36: 9 | B36: 6.6641592 | C36: -0.33653815
A37: 10 | B37: 7.1213206 | C37: -1.1406186
A38: 11 | B38: 6.6966493 | C38: -0.75387335
A39: 12 | B39: 6.2898141 | C39: -0.30212805
... A146: 119 | B146: 3.9252392 | C146: -0.04610815

Sheet Boston
A1: MKT | B1: yearq | C1: COMP | D1: R | E1: STK | F1: CAP | G1: CPI | H1: T10 | L1: CAP | M1: CAP(t-4) | N1: T10 | O1: Rt/Rt-4 | P1: CPIt/CPI(t-4)
A2: Boston | B2: 1987.1 | C2: 1803 | D2: 23.24 | E2: 114459 | F2: 7.570546 | G2: 111.8 | H2: 7.1954098 | L2: 7.570546 | N2: 7.1954098
A3: Boston | B3: 1987.2 | C3: 945 | D3: 22.89 | E3: 115404 | F3: 7.563081 | G3: 113.06667 | H3: 8.3426984 | L3: 7.563081 | N3: 8.3426984
A4: Boston | B4: 1987.3 | C4: 751 | D4: 23.15 | E4: 116155 | F4: 7.571694 | G4: 114.26667 | H4: 8.8696875 | L4: 7.571694 | N4: 8.8696875
A5: Boston | B5: 1987.4 | C5: 5317 | D5: 23.4 | E5: 121472 | F5: 7.082311 | G5: 115.33333 | H5: 9.1290323 | L5: 7.082311 | N5: 9.1290323
A6: Boston | B6: 1988.1 | C6: 2612 | D6: 23.62 | E6: 124084 | F6: 7.031886 | G6: 116.23333 | H6: 8.4109677 | L6: 7.031886 | M6: =F2 -> 7.570546 | N6: 8.4109677 | O6: =D6/D2 -> 1.0163511 | P6: =G6/G2 -> 1.0396541
A7: Boston | B7: 1988.2 | C7: 1666 | D7: 23.84 | E7: 125750 | F7: 6.708543 | G7: 117.56667 | H7: 8.9128571 | L7: 6.708543 | M7: =F3 -> 7.563081 | N7: 8.9128571 | O7: =D7/D3 -> 1.0415028 | P7: =G7/G3 -> 1.0397995
A8: Boston | B8: 1988.3 | C8: 758 | D8: 23.86 | E8: 126508 | F8: 6.696696 | G8: 119 | H8: 9.1035937 | L8: 6.696696 | M8: =F4 -> 7.571694 | N8: 9.1035937 | O8: =D8/D4 -> 1.0306695 | P8: =G8/G4 -> 1.0414236
A9: Boston | B9: 1988.4 | C9: 1839 | D9: 23.88 | E9: 128347 | F9: 6.731336 | G9: 120.3 | H9: 8.9570492 | L9: 6.731336 | M9: =F5 -> 7.082311 | N9: 8.9570492 | O9: =D9/D5 -> 1.0205128 | P9: =G9/G5 -> 1.0430636
A10: Boston | B10: 1989.1 | C10: 1452 | D10: 23.29 | E10: 129799 | F10: 6.730601 | G10: 121.66667 | H10: 9.2116393 | L10: 6.730601 | M10: =F6 -> 7.031886 | N10: 9.2116393 | O10: =D10/D6 -> 0.98602879 | P10: =G10/G6 -> 1.0467451
A11: Boston | B11: 1989.2 | C11: 1915 | D11: 22.73 | E11: 131714 | F11: 6.919796 | G11: 123.63333 | H11: 8.7579687 | L11: 6.919796 | M11: =F7 -> 6.708543 | N11: 8.7579687 | O11: =D11/D7 -> 0.9534396 | P11: =G11/G7 -> 1.0516019
A12: Boston | B12: 1989.3 | C12: 391 | D12: 22.72 | E12: 132105 | F12: 6.794586 | G12: 124.6 | H12: 8.1074603 | L12: 6.794586 | M12: =F8 -> 6.696696 | N12: 8.1074603 | O12: =D12/D8 -> 0.95222129 | P12: =G12/G8 -> 1.0470588
A13: Boston | B13: 1989.4 | C13: 3272 | D13: 22.71 | E13: 135377 | F13: 6.661312 | G13: 125.86667 | H13: 7.9070968 | L13: 6.661312 | M13: =F9 -> 6.731336 | N13: 7.9070968 | O13: =D13/D9 -> 0.95100503 | P13: =G13/G9 -> 1.0462732
A14: Boston | B14: 1990.1 | C14: 1874 | D14: 21.96 | E14: 137251 | F14: 6.327621 | G14: 128.03333 | H14: 8.423871 | L14: 6.327621 | M14: =F10 -> 6.730601 | N14: 8.423871 | O14: =D14/D10 -> 0.94289395 | P14: =G14/G10 -> 1.0523288
A15: Boston | B15: 1990.2 | C15: 0 | D15: 21.25 | E15: 137251 | F15: 5.980702 | G15: 129.3 | H15: 8.674127 | L15: 5.980702 | M15: =F11 -> 6.919796 | N15: 8.674127 | O15: =D15/D11 -> 0.93488781 | P15: =G15/G11 -> 1.0458345
A16: Boston | B16: 1990.3 | C16: 1353 | D16: 21.04 | E16: 138604 | F16: 5.942776 | G16: 131.53333 | H16: 8.7012698 | L16: 5.942776 | M16: =F12 -> 6.794586 | N16: 8.7012698 | O16: =D16/D12 -> 0.92605634 | P16: =G16/G12 -> 1.0556447
A17: Boston | B17: 1990.4 | C17: 811 | D17: 20.82 | E17: 139415 | F17: 5.987686 | G17: 133.76667 | H17: 8.4059677 | L17: 5.987686 | M17: =F13 -> 6.661312 | N17: 8.4059677 | O17: =D17/D13 -> 0.91677675 | P17: =G17/G13 -> 1.0627648
... A124: Boston | B124: 2017.3 | C124: 636 | D124: 36.19 | E124: 189398 | F124: 3.879131 | G124: 245.287 | H124: 2.241429 | L124: 3.879131 | M124: =F120 -> 3.911754 | N124: 2.241429 | O124: =D124/D120 -> 1.0396438 | P124: =G124/G120 -> 1.0194494

Sheet Model 1 Chi
A1: SUMMARY OUTPUT
A3: Regression Statistics
A4: Multiple R | B4: 0.830772
A5: R Square | B5: 0.69018211
A6: Adjusted R Square | B6: 0.68209991
A7: Standard Error | B7: 0.70102627
A8: Observations | B8: 119
A10: ANOVA
B11: df | C11: SS | D11: MS | E11: F | F11: Significance F
A12: Regression | B12: 3 | C12: 125.89939 | D12: 41.966464 | E12: 85.395266 | F12: 3.934295e-29
A13: Residual | B13: 115 | C13: 56.51535 | D13: 0.49143783
A14: Total | B14: 118 | C14: 182.41474
B16: Coefficients | C16: Standard Error | D16: t Stat | E16: P-value | F16: Lower 95% | G16: Upper 95% | H16: Lower 95.0% | I16: Upper 95.0%
A17: Intercept | B17: 4.4476367 | C17: 1.3833532 | D17: 3.215113 | E17: 0.0016929447 | F17: 1.7074803 | G17: 7.1877931 | H17: 1.7074803 | I17: 7.1877931
A18: X Variable 1 | B18: 0.81966888 | C18: 0.057880738 | D18: 14.161341 | E18: 5.7700802e-27 | F18: 0.70501827 | G18: 0.93431948 | H18: 0.70501827 | I18: 0.93431948
A19: X Variable 2 | B19: 0.083104673 | C19: 0.032887715 | D19: 2.5269215 | E19: 0.012865417 | F19: 0.017960439 | G19: 0.14824891 | H19: 0.017960439 | I19: 0.14824891
A20: X Variable 3 | B20: -3.613375 | C20: 1.3825636 | D20: -2.6135325 | E20: 0.010159341 | F20: -6.3519674 | G20: -0.87478255 | H20: -6.3519674 | I20: -0.87478255
A24: RESIDUAL OUTPUT
A26: Observation | B26: Predicted Y | C26: Residuals
A27: 1 | B27: 7.2964368 | C27: -0.42736977
A28: 2 | B28: 7.3190819 | C28: -0.98297593
A29: 3 | B29: 7.4425861 | C29: -1.8157851
A30: 4 | B30: 7.5120235 | C30: -2.3719715
A31: 5 | B31: 7.0966819 | C31: -1.6526299
A32: 6 | B32: 6.7180767 | C32: -1.0430697
A33: 7 | B33: 6.1220183 | C33: -0.14466934
A34: 8 | B34: 5.7476023 | C34: 0.64544768
A35: 9 | B35: 6.022761 | C35: 0.36441597
A36: 10 | B36: 6.2141761 | C36: -0.038972099
A37: 11 | B37: 6.4737098 | C37: -0.18186877
A38: 12 | B38: 6.7976663 | C38: -0.34567629
... A145: 119 | B145: 5.0999417 | C145: 0.15202527

Sheet Model 2 Chi
A1: SUMMARY OUTPUT
A3: Regression Statistics
A4: Multiple R | B4: 0.85431953
A5: R Square | B5: 0.72986186
A6: Adjusted R Square | B6: 0.72038333
A7: Standard Error | B7: 0.65746175
A8: Observations | B8: 119
A10: ANOVA
B11: df | C11: SS | D11: MS | E11: F | F11: Significance F
A12: Regression | B12: 4 | C12: 133.13756 | D12: 33.284391 | E12: 77.001579 | F12: 1.6975699e-31
A13: Residual | B13: 114 | C13: 49.277179 | D13: 0.43225595
A14: Total | B14: 118 | C14: 182.41474
B16: Coefficients | C16: Standard Error | D16: t Stat | E16: P-value | F16: Lower 95% | G16: Upper 95% | H16: Lower 95.0% | I16: Upper 95.0%
A17: Intercept | B17: 30.595863 | C17: 6.5203396 | D17: 4.6923726 | E17: 7.5656025e-06 | F17: 17.679121 | G17: 43.512605 | H17: 17.679121 | I17: 43.512605
A18: X Variable 1 | B18: 0.78059757 | C18: 0.055117113 | D18: 14.162526 | E18: 6.9387677e-27 | F18: 0.671411 | G18: 0.88978415 | H18: 0.671411 | I18: 0.88978415
A19: X Variable 2 | B19: 0.19734729 | C19: 0.041602443 | D19: 4.7436468 | E19: 6.1283598e-06 | F19: 0.11493317 | G19: 0.27976141 | H19: 0.11493317 | I19: 0.27976141
A20: X Variable 3 | B20: -4.1674382 | C20: 1.3036959 | D20: -3.1966337 | E20: 0.0017994548 | F20: -6.7500497 | G20: -1.5848267 | H20: -6.7500497 | I20: -1.5848267
A21: X Variable 4 | B21: -25.217827 | C21: 6.1625963 | D21: -4.0920784 | E21: 8.0086589e-05 | F21: -37.425883 | G21: -13.009771 | H21: -37.425883 | I21: -13.009771
A25: RESIDUAL OUTPUT
A27: Observation | B27: Predicted Y | C27: Residuals
A28: 1 | B28: 7.3393926 | C28: -0.47032557
A29: 2 | B29: 7.3976634 | C29: -1.0615574
A30: 3 | B30: 7.4926903 | C30: -1.8658893
A31: 4 | B31: 7.4955143 | C31: -2.3554623
A32: 5 | B32: 7.0577217 | C32: -1.6136697
A33: 6 | B33: 6.540344 | C33: -0.86533698
A34: 7 | B34: 6.0182916 | C34: -0.0409426
A35: 8 | B35: 5.6661337 | C35: 0.72691626
A36: 9 | B36: 5.8331427 | C36: 0.55403435
A37: 10 | B37: 6.2050306 | C37: -0.029826596
A38: 11 | B38: 6.2099087 | C38: 0.081932326
A39: 12 | B39: 6.3055236 | C39: 0.14646639
... A146: 119 | B146: 5.0311239 | C146: 0.22084309

Sheet Chicago
A1: MKT | B1: yearq | C1: COMP | D1: R | E1: STK | F1: CAP | G1: CPI | H1: T10 | L1: CAP | M1: CAP(t-4) | N1: T10 | O1: Rt/Rt-4 | P1: CPIt/CPI(t-4)
A2: Chicago | B2: 1987.1 | C2: 908 | D2: 18.19 | E2: 152934 | F2: 7.149864 | G2: 111.8 | H2: 7.1954098 | L2: 7.149864 | N2: 7.1954098
A3: Chicago | B3: 1987.2 | C3: 353 | D3: 18.29 | E3: 153287 | F3: 7.241648 | G3: 113.06667 | H3: 8.3426984 | L3: 7.241648 | N3: 8.3426984
A4: Chicago | B4: 1987.3 | C4: 533 | D4: 18.2 | E4: 153820 | F4: 7.398363 | G4: 114.26667 | H4: 8.8696875 | L4: 7.398363 | N4: 8.8696875
A5: Chicago | B5: 1987.4 | C5: 6390 | D5: 18.11 | E5: 160210 | F5: 7.525999 | G5: 115.33333 | H5: 9.1290323 | L5: 7.525999 | N5: 9.1290323
A6: Chicago | B6: 1988.1 | C6: 1085 | D6: 18.68 | E6: 161295 | F6: 6.869067 | G6: 116.23333 | H6: 8.4109677 | L6: 6.869067 | M6: =F2 -> 7.149864 | N6: 8.4109677 | O6: =D6/D2 -> 1.0269379 | P6: =G6/G2 -> 1.0396541
A7: Chicago | B7: 1988.2 | C7: 478 | D7: 19.26 | E7: 161773 | F7: 6.336106 | G7: 117.56667 | H7: 8.9128571 | L7: 6.336106 | M7: =F3 -> 7.241648 | N7: 8.9128571 | O7: =D7/D3 -> 1.0530344 | P7: =G7/G3 -> 1.0397995
A8: Chicago | B8: 1988.3 | C8: 282 | D8: 19.27 | E8: 162055 | F8: 5.626801 | G8: 119 | H8: 9.1035937 | L8: 5.626801 | M8: =F4 -> 7.398363 | N8: 9.1035937 | O8: =D8/D4 -> 1.0587912 | P8: =G8/G4 -> 1.0414236
A9: Chicago | B9: 1988.4 | C9: 1054 | D9: 19.29 | E9: 163109 | F9: 5.140052 | G9: 120.3 | H9: 8.9570492 | L9: 5.140052 | M9: =F5 -> 7.525999 | N9: 8.9570492 | O9: =D9/D5 -> 1.0651574 | P9: =G9/G5 -> 1.0430636
A10: Chicago | B10: 1989.1 | C10: 915 | D10: 19.37 | E10: 164024 | F10: 5.444052 | G10: 121.66667 | H10: 9.2116393 | L10: 5.444052 | M10: =F6 -> 6.869067 | N10: 9.2116393 | O10: =D10/D6 -> 1.0369379 | P10: =G10/G6 -> 1.0467451
A11: Chicago | B11: 1989.2 | C11: 6702 | D11: 19.46 | E11: 170726 | F11: 5.675007 | G11: 123.63333 | H11: 8.7579687 | L11: 5.675007 | M11: =F7 -> 6.336106 | N11: 8.7579687 | O11: =D11/D7 -> 1.0103842 | P11: =G11/G7 -> 1.0516019
A12: Chicago | B12: 1989.3 | C12: 290 | D12: 19.26 | E12: 171016 | F12: 5.977349 | G12: 124.6 | H12: 8.1074603 | L12: 5.977349 | M12: =F8 -> 5.626801 | N12: 8.1074603 | O12: =D12/D8 -> 0.99948106 | P12: =G12/G8 -> 1.0470588
A13: Chicago | B13: 1989.4 | C13: 1166 | D13: 19.06 | E13: 172182 | F13: 6.39305 | G13: 125.86667 | H13: 7.9070968 | L13: 6.39305 | M13: =F9 -> 5.140052 | N13: 7.9070968 | O13: =D13/D9 -> 0.98807672 | P13: =G13/G9 -> 1.0462732
A14: Chicago | B14: 1990.1 | C14: 2800 | D14: 19.23 | E14: 174982 | F14: 6.387177 | G14: 128.03333 | H14: 8.423871 | L14: 6.387177 | M14: =F10 -> 5.444052 | N14: 8.423871 | O14: =D14/D10 -> 0.99277233 | P14: =G14/G10 -> 1.0523288
A15: Chicago | B15: 1990.2 | C15: 3390 | D15: 19.42 | E15: 178372 | F15: 6.175204 | G15: 129.3 | H15: 8.674127 | L15: 6.175204 | M15: =F11 -> 5.675007 | N15: 8.674127 | O15: =D15/D11 -> 0.9979445 | P15: =G15/G11 -> 1.0458345
A16: Chicago | B16: 1990.3 | C16: 2001 | D16: 19.17 | E16: 180373 | F16: 6.291841 | G16: 131.53333 | H16: 8.7012698 | L16: 6.291841 | M16: =F12 -> 5.977349 | N16: 8.7012698 | O16: =D16/D12 -> 0.9953271 | P16: =G16/G12 -> 1.0556447
A17: Chicago | B17: 1990.4 | C17: 552 | D17: 18.93 | E17: 180925 | F17: 6.45199 | G17: 133.76667 | H17: 8.4059677 | L17: 6.45199 | M17: =F13 -> 6.39305 | N17: 8.4059677 | O17: =D17/D13 -> 0.99317943 | P17: =G17/G13 -> 1.0627648
... A124: Chicago | B124: 2017.3 | C124: 420 | D124: 25.52 | E124: 236022 | F124: 5.251967 | G124: 245.287 | H124: 2.241429 | L124: 5.251967 | M124: =F120 -> 5.075801 | N124: 2.241429 | O124: =D124/D120 -> 1.0224359 | P124: =G124/G120 -> 1.0194494

Sheet Model1 Dallas
A1: SUMMARY OUTPUT
A3: Regression Statistics
A4: Multiple R | B4: 0.89523553
A5: R Square | B5: 0.80144665
A6: Adjusted R Square | B6: 0.79626699
A7: Standard Error | B7: 0.81013697
A8: Observations | B8: 119
A10: ANOVA
B11: df | C11: SS | D11: MS | E11: F | F11: Significance F
A12: Regression | B12: 3 | C12: 304.65768 | D12: 101.55256 | E12: 154.7298 | F12: 3.2801946e-40
A13: Residual | B13: 115 | C13: 75.477021 | D13: 0.65632192
A14: Total | B14: 118 | C14: 380.13471
B16: Coefficients | C16: Standard Error | D16: t Stat | E16: P-value | F16: Lower 95% | G16: Upper 95% | H16: Lower 95.0% | I16: Upper 95.0%
A17: Intercept | B17: 2.0865651 | C17: 1.0204254 | D17: 2.0447993 | E17: 0.043157485 | F17: 0.065298813 | G17: 4.1078313 | H17: 0.065298813 | I17: 4.1078313
A18: X Variable 1 | B18: 0.8378277 | C18: 0.041985285 | D18: 19.95527 | E18: 3.738467e-39 | F18: 0.75466293 | G18: 0.92099247 | H18: 0.75466293 | I18: 0.92099247
A19: X Variable 2 | B19: 0.161694 | C19: 0.036020644 | D19: 4.4889258 | E19: 1.7097451e-05 | F19: 0.090344036 | G19: 0.23304396 | H19: 0.090344036 | I19: 0.23304396
A20: X Variable 3 | B20: -1.6451235 | C20: 0.98135231 | D20: -1.6763842 | E20: 0.096379504 | F20: -3.5889936 | G20: 0.29874654 | H20: -3.5889936 | I20: 0.29874654
A24: RESIDUAL OUTPUT
A26: Observation | B26: Predicted Y | C26: Residuals
A27: 1 | B27: 5.5686948 | C27: -0.79250881
A28: 2 | B28: 5.6883295 | C28: -0.92549252
A29: 3 | B29: 5.7840723 | C29: -1.1671123
A30: 4 | B30: 5.8917935 | C30: -1.3968135
A31: 5 | B31: 6.0405275 | C31: -1.4235705
A32: 6 | B32: 5.8846835 | C32: -1.0830015
A33: 7 | B33: 5.6096292 | C33: -0.37766317
A34: 8 | B34: 5.4266634 | C34: 0.15894864
A35: 9 | B35: 5.5371588 | C35: 0.1525242
A36: 10 | B36: 5.6543005 | C36: 0.39304553
A37: 11 | B37: 6.00174 | C37: 0.29012097
A38: 12 | B38: 6.2312492 | C38: 0.28200277
... A145: 119 | B145: 5.4109491 | C145: -0.71367408

Sheet Model 2 DAL
A1: SUMMARY OUTPUT
A3: Regression Statistics
A4: Multiple R | B4: 0.90011958
A5: R Square | B5: 0.81021525
A6: Adjusted R Square | B6: 0.80355614
A7: Standard Error | B7: 0.79551247
A8: Observations | B8: 119
A10: ANOVA
B11: df | C11: SS | D11: MS | E11: F | F11: Significance F
A12: Regression | B12: 4 | C12: 307.99094 | D12: 76.997734 | E12: 121.67013 | F12: 3.425103e-40
A13: Residual | B13: 114 | C13: 72.14377 | D13: 0.63284009
A14: Total | B14: 118 | C14: 380.13471
B16: Coefficients | C16: Standard Error | D16: t Stat | E16: P-value | F16: Lower 95% | G16: Upper 95% | H16: Lower 95.0% | I16: Upper 95.0%
A17: Intercept | B17: 19.56788 | C17: 7.6826783 | D17: 2.5470128 | E17: 0.012197557 | F17: 4.3485534 | G17: 34.787207 | H17: 4.3485534 | I17: 34.787207
A18: X Variable 1 | B18: 0.81185704 | C18: 0.042752191 | D18: 18.989835 | E18: 4.1993641e-37 | F18: 0.72716528 | G18: 0.8965488 | H18: 0.72716528 | I18: 0.8965488
A19: X Variable 2 | B19: 0.23735651 | C19: 0.048352459 | D19: 4.9088819 | E19: 3.0795212e-06 | F19: 0.14157066 | G19: 0.33314236 | H19: 0.14157066 | I19: 0.33314236
A20: X Variable 3 | B20: -1.5187948 | C20: 0.96520788 | D20: -1.5735416 | E20: 0.11836475 | F20: -3.4308641 | G20: 0.39327462 | H20: -3.4308641 | I20: 0.39327462
A21: X Variable 4 | B21: -17.343633 | C21: 7.5570638 | D21: -2.2950227 | E21: 0.023561504 | F21: -32.314118 | G21: -2.3731477 | H21: -32.314118 | I21: -2.3731477
A25: RESIDUAL OUTPUT
A27: Observation | B27: Predicted Y | C27: Residuals
A28: 1 | B28: 5.6588791 | C28: -0.8826931
A29: 2 | B29: 5.8100742 | C29: -1.0472372
A30: 3 | B30: 5.8902324 | C30: -1.2732724
A31: 4 | B31: 5.9545195 | C31: -1.4595395
A32: 5 | B32: 6.058451 | C32: -1.441494
A33: 6 | B33: 5.7898674 | C33: -0.9881854
A34: 7 | B34: 5.5518355 | C34: -0.31986952
A35: 8 | B35: 5.3742174 | C35: 0.21139461
A36: 9 | B36: 5.4213992 | C36: 0.26828382
A37: 10 | B37: 5.6713099 | C37: 0.37603606
A38: 11 | B38: 5.8408229 | C38: 0.45103812
A39: 12 | B39: 5.9167778 | C39: 0.59647423
... A146: 119 | B146: 5.3663477 | C146: -0.66907268

Sheet Dallas
A1: MKT | B1: yearq | C1: COMP | D1: R | E1: STK | F1: CAP | G1: CPI | H1: T10 | L1: CAP | M1: CAP(t-4) | N1: T10 | O1: Rt/Rt-4 | P1: CPIt/CPI(t-4)
A2: Dallas | B2: 1987.1 | C2: 236 | D2: 12.03 | E2: 102105 | F2: 4.347918 | G2: 111.8 | H2: 7.1954098 | L2: 4.347918 | N2: 7.1954098
A3: Dallas | B3: 1987.2 | C3: 866 | D3: 12.11 | E3: 102971 | F3: 4.323487 | G3: 113.06667 | H3: 8.3426984 | L3: 4.323487 | N3: 8.3426984
A4: Dallas | B4: 1987.3 | C4: 274 | D4: 11.8 | E4: 103245 | F4: 4.405185 | G4: 114.26667 | H4: 8.8696875 | L4: 4.405185 | N4: 8.8696875
A5: Dallas | B5: 1987.4 | C5: 4340 | D5: 11.49 | E5: 107585 | F5: 4.566501 | G5: 115.33333 | H5: 9.1290323 | L5: 4.566501 | N5: 9.1290323
A6: Dallas | B6: 1988.1 | C6: 443 | D6: 11.12 | E6: 108028 | F6: 4.776186 | G6: 116.23333 | H6: 8.4109677 | L6: 4.776186 | M6: =F2 -> 4.347918 | N6: 8.4109677 | O6: =D6/D2 -> 0.92435578 | P6: =G6/G2 -> 1.0396541
A7: Dallas | B7: 1988.2 | C7: 0 | D7: 10.76 | E7: 108028 | F7: 4.762837 | G7: 117.56667 | H7: 8.9128571 | L7: 4.762837 | M7: =F3 -> 4.323487 | N7: 8.9128571 | O7: =D7/D3 -> 0.88852188 | P7: =G7/G3 -> 1.0397995
A8: Dallas | B8: 1988.3 | C8: 0 | D8: 10.51 | E8: 108028 | F8: 4.61696 | G8: 119 | H8: 9.1035937 | L8: 4.61696 | M8: =F4 -> 4.405185 | N8: 9.1035937 | O8: =D8/D4 -> 0.89067797 | P8: =G8/G4 -> 1.0414236
A9: Dallas | B9: 1988.4 | C9: 0 | D9: 10.26 | E9: 108028 | F9: 4.49498 | G9: 120.3 | H9: 8.9570492 | L9: 4.49498 | M9: =F5 -> 4.566501 | N9: 8.9570492 | O9: =D9/D5 -> 0.89295039 | P9: =G9/G5 -> 1.0430636
A10: Dallas | B10: 1989.1 | C10: 0 | D10: 10.39 | E10: 108028 | F10: 4.616957 | G10: 121.66667 | H10: 9.2116393 | L10: 4.616957 | M10: =F6 -> 4.776186 | N10: 9.2116393 | O10: =D10/D6 -> 0.93435252 | P10: =G10/G6 -> 1.0467451
A11: Dallas | B11: 1989.2 | C11: 383 | D11: 10.52 | E11: 108411 | F11: 4.801682 | G11: 123.63333 | H11: 8.7579687 | L11: 4.801682 | M11: =F7 -> 4.762837 | N11: 8.7579687 | O11: =D11/D7 -> 0.97769517 | P11: =G11/G7 -> 1.0516019
A12: Dallas | B12: 1989.3 | C12: 0 | D12: 10.58 | E12: 108411 | F12: 5.231966 | G12: 124.6 | H12: 8.1074603 | L12: 5.231966 | M12: =F8 -> 4.61696 | N12: 8.1074603 | O12: =D12/D8 -> 1.0066603 | P12: =G12/G8 -> 1.0470588
A13: Dallas | B13: 1989.4 | C13: 0 | D13: 10.63 | E13: 108411 | F13: 5.585612 | G13: 125.86667 | H13: 7.9070968 | L13: 5.585612 | M13: =F9 -> 4.49498 | N13: 7.9070968 | O13: =D13/D9 -> 1.0360624 | P13: =G13/G9 -> 1.0462732
A14: Dallas | B14: 1990.1 | C14: 0 | D14: 11.24 | E14: 108411 | F14: 5.689683 | G14: 128.03333 | H14: 8.423871 | L14: 5.689683 | M14: =F10 -> 4.616957 | N14: 8.423871 | O14: =D14/D10 -> 1.0818094 | P14: =G14/G10 -> 1.0523288
A15: Dallas | B15: 1990.2 | C15: 0 | D15: 11.88 | E15: 108411 | F15: 6.047346 | G15: 129.3 | H15: 8.674127 | L15: 6.047346 | M15: =F11 -> 4.801682 | N15: 8.674127 | O15: =D15/D11 -> 1.1292776 | P15: =G15/G11 -> 1.0458345
A16: Dallas | B16: 1990.3 | C16: 0 | D16: 12.06 | E16: 108411 | F16: 6.291861 | G16: 131.53333 | H16: 8.7012698 | L16: 6.291861 | M16: =F12 -> 5.231966 | N16: 8.7012698 | O16: =D16/D12 -> 1.1398866 | P16: =G16/G12 -> 1.0556447
A17: Dallas | B17: 1990.4 | C17: 0 | D17: 12.24 | E17: 108411 | F17: 6.513252 | G17: 133.76667 | H17: 8.4059677 | L17: 6.513252 | M17: =F13 -> 5.585612 | N17: 8.4059677 | O17: =D17/D13 -> 1.1514581 | P17: =G17/G13 -> 1.0627648
... A124: Dallas | B124: 2017.3 | C124: 656 | D124: 24.05 | E124: 162757 | F124: 4.697275 | G124: 245.287 | H124: 2.241429 | L124: 4.697275 | M124: =F120 -> 5.549082 | N124: 2.241429 | O124: =D124/D120 -> 1.0255864 | P124: =G124/G120 -> 1.0194494

Sheet Model1 NY
A1: SUMMARY OUTPUT
A3: Regression Statistics
A4: Multiple R | B4: 0.90168058
A5: R Square | B5: 0.81302786
A6: Adjusted R Square | B6: 0.80815033
A7: Standard Error | B7: 0.73478161
A8: Observations | B8: 119
A10: ANOVA
B11: df | C11: SS | D11: MS | E11: F | F11: Significance F
A12: Regression | B12: 3 | C12: 269.98704 | D12: 89.995682 | E12: 166.6883 | F12: 1.0427506e-41
A13: Residual | B13: 115 | C13: 62.088961 | D13: 0.53990401
A14: Total | B14: 118 | C14: 332.07601
B16: Coefficients | C16: Standard Error | D16: t Stat | E16: P-value | F16: Lower 95% | G16: Upper 95% | H16: Lower 95.0% | I16: Upper 95.0%
A17: Intercept | B17: 4.1982003 | C17: 0.84202726 | D17: 4.9858246 | E17: 2.2030367e-06 | F17: 2.5303063 | G17: 5.8660942 | H17: 2.5303063 | I17: 5.8660942
A18: X Variable 1 | B18: 0.80544029 | C18: 0.05440632 | D18: 14.804168 | E18: 2.1028449e-28 | F18: 0.69767184 | G18: 0.91320874 | H18: 0.69767184 | I18: 0.91320874
A19: X Variable 2 | B19: 0.12301428 | C19: 0.04119061 | D19: 2.9864641 | E19: 0.0034495787 | F19: 0.041423606 | G19: 0.20460495 | H19: 0.041423606 | I19: 0.20460495
A20: X Variable 3 | B20: -3.5382127 | C20: 0.75060331 | D20: -4.7138251 | E20: 6.8724186e-06 | F20: -5.0250134 | G20: -2.051412 | H20: -5.0250134 | I20: -2.051412
A24: RESIDUAL OUTPUT
A26: Observation | B26: Predicted Y | C26: Residuals
A27: 1 | B27: 7.8189879 | C27: -0.26444688
A28: 2 | B28: 7.9278071 | C28: -0.51158212
A29: 3 | B29: 7.9923251 | C29: -0.74168609
A30: 4 | B30: 7.7774653 | C30: -0.47741934
A31: 5 | B31: 7.9059857 | C31: -1.0480057
A32: 6 | B32: 7.8391801 | C32: -1.2199141
A33: 7 | B33: 7.6449724 | C33: -1.1957134
A34: 8 | B34: 7.6357104 | C34: -1.4676124
A35: 9 | B35: 7.259597 | C35: -0.99322102
A36: 10 | B36: 7.0267928 | C36: -0.73721879
A37: 11 | B37: 6.8738059 | C37: -0.6817539
A38: 12 | B38: 6.6169361 | C38: -0.20612014
... A145: 119 | B145: 3.8339099 | C145: -0.13799393

Sheet Model 2 NY
A1: SUMMARY OUTPUT
A3: Regression Statistics
A4: Multiple R | B4: 0.91298833
A5: R Square | B5: 0.83354769
A6: Adjusted R Square | B6: 0.82770726
A7: Standard Error | B7: 0.69632379
A8: Observations | B8: 119
A10: ANOVA
B11: df | C11: SS | D11: MS | E11: F | F11: Significance F
A12: Regression | B12: 4 | C12: 276.80119 | D12: 69.200297 | E12: 142.72021 | F12: 1.9923746e-43
A13: Residual | B13: 114 | C13: 55.274818 | D13: 0.48486682
A14: Total | B14: 118 | C14: 332.07601
B16: Coefficients | C16: Standard Error | D16: t Stat | E16: P-value | F16: Lower 95% | G16: Upper 95% | H16: Lower 95.0% | I16: Upper 95.0%
A17: Intercept | B17: 29.253255 | C17: 6.7309204 | D17: 4.3461003 | E17: 3.0248639e-05 | F17: 15.919353 | G17: 42.587156 | H17: 15.919353 | I17: 42.587156
A18: X Variable 1 | B18: 0.77762865 | C18: 0.05208975 | D18: 14.928631 | E18: 1.3772434e-28 | F18: 0.67443925 | G18: 0.88081804 | H18: 0.67443925 | I18: 0.88081804
A19: X Variable 2 | B19: 0.24424366 | C19: 0.050689822 | D19: 4.8183965 | E19: 4.4966843e-06 | F19: 0.14382752 | G19: 0.34465981 | H19: 0.14382752 | I19: 0.34465981
A20: X Variable 3 | B20: -2.5508964 | C20: 0.75850827 | D20: -3.3630436 | E20: 0.0010502864 | F20: -4.0534954 | G20: -1.0482973 | H20: -4.0534954 | I20: -1.0482973
A21: X Variable 4 | B21: -25.804413 | C21: 6.8833458 | D21: -3.7488184 | E21: 0.00028067377 | F21: -39.440268 | G21: -12.168558 | H21: -39.440268 | I21: -12.168558
A25: RESIDUAL OUTPUT
A27: Observation | B27: Predicted Y | C27: Residuals
A28: 1 | B28: 7.8882126 | C28: -0.33367161
A29: 2 | B29: 8.0476211 | C29: -0.63139611
A30: 3 | B30: 8.0810943 | C30: -0.83045535
A31: 4 | B31: 7.809207 | C31: -0.50916096
A32: 5 | B32: 7.8364899 | C32: -0.97850991
A33: 6 | B33: 7.565186 | C33: -0.94591996
A34: 7 | B34: 7.4086018 | C34: -0.95934279
A35: 8 | B35: 7.4007592 | C35: -1.2326612
A36: 9 | B36: 6.9666639 | C36: -0.70028785
A37: 10 | B37: 6.9583201 | C37: -0.66874614
A38: 11 | B38: 6.5656158 | C38: -0.37356376
A39: 12 | B39: 6.0953857 | C39: 0.31543032
... A146: 119 | B146: 3.770149 | C146: -0.074232952

Sheet NewYork
A1: MKT | B1: yearq | C1: COMP | D1: R | E1: STK | F1: CAP | G1: CPI | H1: T10 | L1: CAP | M1: CAP(t-4) | N1: T10 | O1: Rt/Rt-4 | P1: CPIt/CPI(t-4)
A2: NewYork | B2: 1987.1 | C2: 2627 | D2: 35.85 | E2: 412387 | F2: 7.838974 | G2: 111.8 | H2: 7.1954098 | L2: 7.838974 | N2: 7.1954098
A3: NewYork | B3: 1987.2 | C3: 1286 | D3: 36.52 | E3: 413673 | F3: 7.872661 | G3: 113.06667 | H3: 8.3426984 | L3: 7.872661 | N3: 8.3426984
A4: NewYork | B4: 1987.3 | C4: 3334 | D4: 37.02 | E4: 417007 | F4: 7.868578 | G4: 114.26667 | H4: 8.8696875 | L4: 7.868578 | N4: 8.8696875
A5: NewYork | B5: 1987.4 | C5: 5300 | D5: 37.02 | E5: 422307 | F5: 7.605213 | G5: 115.33333 | H5: 9.1290323 | L5: 7.605213 | N5: 9.1290323
A6: NewYork | B6: 1988.1 | C6: 3826 | D6: 37.77 | E6: 426133 | F6: 7.554541 | G6: 116.23333 | H6: 8.4109677 | L6: 7.554541 | M6: =F2 -> 7.838974 | N6: 8.4109677 | O6: =D6/D2 -> 1.0535565 | P6: =G6/G2 -> 1.0396541
A7: NewYork | B7: 1988.2 | C7: 2201 | D7: 38.27 | E7: 428334 | F7: 7.416225 | G7: 117.56667 | H7: 8.9128571 | L7: 7.416225 | M7: =F3 -> 7.872661 | N7: 8.9128571 | O7: =D7/D3 -> 1.0479189 | P7: =G7/G3 -> 1.0397995
A8: NewYork | B8: 1988.3 | C8: 1771 | D8: 38.33 | E8: 430105 | F8: 7.250639 | G8: 119 | H8: 9.1035937 | L8: 7.250639 | M8: =F4 -> 7.868578 | N8: 9.1035937 | O8: =D8/D4 -> 1.0353863 | P8: =G8/G4 -> 1.0414236
A9: NewYork | B9: 1988.4 | C9: 2673 | D9: 38.17 | E9: 432778 | F9: 7.300046 | G9: 120.3 | H9: 8.9570492 | L9: 7.300046 | M9: =F5 -> 7.605213 | N9: 8.9570492 | O9: =D9/D5 -> 1.0310643 | P9: =G9/G5 -> 1.0430636
A10: NewYork | B10: 1989.1 | C10: 2067 | D10: 37.47 | E10: 434845 | F10: 6.85798 | G10: 121.66667 | H10: 9.2116393 | L10: 6.85798 | M10: =F6 -> 7.554541 | N10: 9.2116393 | O10: =D10/D6 -> 0.99205719 | P10: =G10/G6 -> 1.0467451
A11: NewYork | B11: 1989.2 | C11: 4499 | D11: 36.88 | E11: 439344 | F11: 6.619266 | G11: 123.63333 | H11: 8.7579687 | L11: 6.619266 | M11: =F7 -> 7.416225 | N11: 8.7579687 | O11: =D11/D7 -> 0.96367912 | P11: =G11/G7 -> 1.0516019
A12: NewYork | B12: 1989.3 | C12: 1020 | D12: 36.73 | E12: 440364 | F12: 6.449259 | G12: 124.6 | H12: 8.1074603 | L12: 6.449259 | M12: =F8 -> 7.250639 | N12: 8.1074603 | O12: =D12/D8 -> 0.95825724 | P12: =G12/G8 -> 1.0470588
A13: NewYork | B13: 1989.4 | C13: 4925 | D13: 36.84 | E13: 445289 | F13: 6.168098 | G13: 125.86667 | H13: 7.9070968 | L13: 6.168098 | M13: =F9 -> 7.300046 | N13: 7.9070968 | O13: =D13/D9 -> 0.96515588 | P13: =G13/G9 -> 1.0462732
A14: NewYork | B14: 1990.1 | C14: 2236 | D14: 37.05 | E14: 447525 | F14: 6.266376 | G14: 128.03333 | H14: 8.423871 | L14: 6.266376 | M14: =F10 -> 6.85798 | N14: 8.423871 | O14: =D14/D10 -> 0.98879103 | P14: =G14/G10 -> 1.0523288
A15: NewYork | B15: 1990.2 | C15: 3414 | D15: 37.21 | E15: 450939 | F15: 6.289574 | G15: 129.3 | H15: 8.674127 | L15: 6.289574 | M15: =F11 -> 6.619266 | N15: 8.674127 | O15: =D15/D11 -> 1.0089479 | P15: =G15/G11 -> 1.0458345
A16: NewYork | B16: 1990.3 | C16: 1614 | D16: 37.26 | E16: 452553 | F16: 6.192052 | G16: 131.53333 | H16: 8.7012698 | L16: 6.192052 | M16: =F12 -> 6.449259 | N16: 8.7012698 | O16: =D16/D12 -> 1.0144296 | P16: =G16/G12 -> 1.0556447
A17: NewYork | B17: 1990.4 | C17: 44 | D17: 37.31 | E17: 452597 | F17: 6.410816 | G17: 133.76667 | H17: 8.4059677 | L17: 6.410816 | M17: =F13 -> 6.168098 | N17: 8.4059677 | O17: =D17/D13 -> 1.0127579 | P17: =G17/G13 -> 1.0627648
... A124: NewYork | B124: 2017.3 | C124: 86 | D124: 68.65 | E124: 509805 | F124: 3.695916 | G124: 245.287 | H124: 2.241429 | L124: 3.695916 | M124: =F120 -> 3.743029 | N124: 2.241429 | O124: =D124/D120 -> 1.0329522 | P124: =G124/G120 -> 1.0194494

Sheet Model1 OC
A1: SUMMARY OUTPUT
A3: Regression Statistics
A4: Multiple R | B4: 0.93010374
A5: R Square | B5: 0.86509296
A6: Adjusted R Square | B6: 0.86157365
A7: Standard Error | B7: 0.58152413
A8: Observations | B8: 119
A10: ANOVA
B11: df | C11: SS | D11: MS | E11: F | F11: Significance F
A12: Regression | B12: 3 | C12: 249.37993 | D12: 83.126645 | E12: 245.81295 | F12: 7.6068299e-50
A13: Residual | B13: 115 | C13: 38.889587 | D13: 0.33817032
A14: Total | B14: 118 | C14: 288.26952
B16: Coefficients | C16: Standard Error | D16: t Stat | E16: P-value | F16: Lower 95% | G16: Upper 95% | H16: Lower 95.0% | I16: Upper 95.0%
A17: Intercept | B17: 4.438903 | C17: 0.76834014 | D17: 5.7772629 | E17: 6.5950646e-08 | F17: 2.916969 | G17: 5.9608369 | H17: 2.916969 | I17: 5.9608369
A18: X Variable 1 | B18: 0.91606645 | C18: 0.050065343 | D18: 18.297417 | E18: 7.503398e-36 | F18: 0.81689664 | G18: 1.0152363 | H18: 0.81689664 | I18: 1.0152363
A19: X Variable 2 | B19: 0.041569462 | C19: 0.036075183 | D19: 1.1523008 | E19: 0.25158724 | F19: -0.029888533 | G19: 0.11302746 | H19: -0.029888533 | I19: 0.11302746
A20: X Variable 3 | B20: -4.1194908 | C20: 0.7524063 | D20: -5.4750881 | E20: 2.6011128e-07 | F20: -5.6098629 | G20: -2.6291187 | H20: -5.6098629 | I20: -2.6291187
A24: RESIDUAL OUTPUT
A26: Observation | B26: Predicted Y | C26: Residuals
A27: 1 | B27: 8.1562023 | C27: -0.13729832
A28: 2 | B28: 8.1350702 | C28: -0.096466193
A29: 3 | B29: 8.1636641 | C29: -0.3063421
A30: 4 | B30: 8.0929451 | C30: -0.52020406
A31: 5 | B31: 8.105186 | C31: -0.58337596
A32: 6 | B32: 8.1628307 | C32: -0.89568165
A33: 7 | B33: 7.9835459 | C33: -0.91850188
A34: 8 | B34: 7.7241735 | C34: -0.67484045
A35: 9 | B35: 7.640099 | C35: -0.776729
A36: 10 | B36: 7.3573539 | C36: -0.79751294
A37: 11 | B37: 7.141858 | C37: -0.66615997
A38: 12 | B38: 7.0831381 | C38: -0.4634141
... A145: 119 | B145: 4.3536303 | C145: -0.10074633

Sheet Model 2 OC
A1: SUMMARY OUTPUT
A3: Regression Statistics
A4: Multiple R | B4: 0.93382605
A5: R Square | B5: 0.87203109
A6: Adjusted R Square | B6: 0.86754095
A7: Standard Error | B7: 0.56885185
A8: Observations | B8: 119
A10: ANOVA
B11: df | C11: SS | D11: MS | E11: F | F11: Significance F
A12: Regression | B12: 4 | C12: 251.37998 | D12: 62.844996 | E12: 194.21034 | F12: 6.4567276e-50
A13: Residual | B13: 114 | C13: 36.889537 | D13: 0.32359243
A14: Total | B14: 118 | C14: 288.26952
B16: Coefficients | C16: Standard Error | D16: t Stat | E16: P-value | F16: Lower 95% | G16: Upper 95% | H16: Lower 95.0% | I16: Upper 95.0%
A17: Intercept | B17: 17.845047 | C17: 5.4445337 | D17: 3.277608 | E17: 0.0013880042 | F17: 7.0594678 | G17: 28.630626 | H17: 7.0594678 | I17: 28.630626
A18: X Variable 1 | B18: 0.88508728 | C18: 0.050534738 | D18: 17.514433 | E18: 4.1082718e-34 | F18: 0.78497835 | G18: 0.98519621 | H18: 0.78497835 | I18: 0.98519621
A19: X Variable 2 | B19: 0.11294398 | C19: 0.045492182 | D19: 2.482712 | E19: 0.014494952 | F19: 0.022824323 | G19: 0.20306365 | H19: 0.022824323 | I19: 0.20306365
A20: X Variable 3 | B20: -3.9468343 | C20: 0.73927948 | D20: -5.3387581 | E20: 4.8289172e-07 | F20: -5.4113412 | G20: -2.4823273 | H20: -5.4113412 | I20: -2.4823273
A21: X Variable 4 | B21: -13.374113 | C21: 5.3795226 | D21: -2.4861152 | E21: 0.014364289 | F21: -24.030906 | G21: -2.71732 | H21: -24.030906 | I21: -2.71732
A25: RESIDUAL OUTPUT
A27: Observation | B27: Predicted Y | C27: Residuals
A28: 1 | B28: 8.1761745 | C28: -0.15727053
A29: 2 | B29: 8.1913961 | C29: -0.15279205
A30: 3 | B30: 8.211443 | C30: -0.35412102
A31: 4 | B31: 8.110746 | C31: -0.53800496
A32: 5 | B32: 8.0913685 | C32: -0.56955852
A33: 6 | B33: 8.0486159 | C33: -0.78146695
A34: 7 | B34: 7.8886981 | C34: -0.82365405
A35: 8 | B35: 7.6339433 | C35: -0.58461027
A36: 9 | B36: 7.509812 | C36: -0.64644201
A37: 10 | B37: 7.3421826 | C37: -0.78234161
A38: 11 | B38: 7.0050008 | C38: -0.52930279
A39: 12 | B39: 6.8318089 | C39: -0.21208494
... A146: 119 | B146: 4.3277043 | C146: -0.074820271

Sheet OrangeCounty
A1: MKT | B1: yearq | C1: COMP | D1: R | E1: STK | F1: CAP | G1: CPI | H1: T10 | L1: CAP | M1: CAP(t-4) | N1: T10 | O1: Rt/Rt-4 | P1: CPIt/CPI(t-4)
A2: OrangeCounty | B2: 1987.1 | C2: 304 | D2: 19.68 | E2: 34721 | F2: 7.969785 | G2: 111.8 | H2: 7.1954098 | L2: 7.969785 | N2: 7.1954098
A3: OrangeCounty | B3: 1987.2 | C3: 592 | D3: 19.17 | E3: 35313 | F3: 8.066318 | G3: 113.06667 | H3: 8.3426984 | L3: 8.066318 | N3: 8.3426984
A4: OrangeCounty | B4: 1987.3 | C4: 882 | D4: 18.91 | E4: 36195 | F4: 8.123709 | G4: 114.26667 | H4: 8.8696875 | L4: 8.123709 | N4: 8.8696875
A5: OrangeCounty | B5: 1987.4 | C5: 4010 | D5: 18.66 | E5: 40205 | F5: 8.084139 | G5: 115.33333 | H5: 9.1290323 | L5: 8.084139 | N5: 9.1290323
A6: OrangeCounty | B6: 1988.1 | C6: 1233 | D6: 18.79 | E6: 41438 | F6: 8.018904 | G6: 116.23333 | H6: 8.4109677 | L6: 8.018904 | M6: =F2 -> 7.969785 | N6: 8.4109677 | O6: =D6/D2 -> 0.95477642 | P6: =G6/G2 -> 1.0396541
A7: OrangeCounty | B7: 1988.2 | C7: 1008 | D7: 18.91 | E7: 42446 | F7: 8.038604 | G7: 117.56667 | H7: 8.9128571 | L7: 8.038604 | M7: =F3 -> 8.066318 | N7: 8.9128571 | O7: =D7/D3 -> 0.98643714 | P7: =G7/G3 -> 1.0397995
A8: OrangeCounty | B8: 1988.3 | C8: 726 | D8: 18.8 | E8: 43172 | F8: 7.857322 | G8: 119 | H8: 9.1035937 | L8: 7.857322 | M8: =F4 -> 8.123709 | N8: 9.1035937 | O8: =D8/D4 -> 0.99418297 | P8: =G8/G4 -> 1.0414236
A9: OrangeCounty | B9: 1988.4 | C9: 172 | D9: 18.68 | E9: 43344 | F9: 7.572741 | G9: 120.3 | H9: 8.9570492 | L9: 7.572741 | M9: =F5 -> 8.084139 | N9: 8.9570492 | O9: =D9/D5 -> 1.0010718 | P9: =G9/G5 -> 1.0430636
A10: OrangeCounty | B10: 1989.1 | C10: 1905 | D10: 18.53 | E10: 45249 | F10: 7.52181 | G10: 121.66667 | H10: 9.2116393 | L10: 7.52181 | M10: =F6 -> 8.018904 | N10: 9.2116393 | O10: =D10/D6 -> 0.98616285 | P10: =G10/G6 -> 1.0467451
A11: OrangeCounty | B11: 1989.2 | C11: 664 | D11: 18.38 | E11: 45913 | F11: 7.267149 | G11: 123.63333 | H11: 8.7579687 | L11: 7.267149 | M11: =F7 -> 8.038604 | N11: 8.7579687 | O11: =D11/D7 -> 0.9719725 | P11: =G11/G7 -> 1.0516019
A12: OrangeCounty | B12: 1989.3 | C12: 841 | D12: 18.21 | E12: 46754 | F12: 7.065044 | G12: 124.6 | H12: 8.1074603 | L12: 7.065044 | M12: =F8 -> 7.857322 | N12: 8.1074603 | O12: =D12/D8 -> 0.96861702 | P12: =G12/G8 -> 1.0470588
A13: OrangeCounty | B13: 1989.4 | C13: 835 | D13: 18.05 | E13: 47589 | F13: 7.049333 | G13: 125.86667 | H13: 7.9070968 | L13: 7.049333 | M13: =F9 -> 7.572741 | N13: 7.9070968 | O13: =D13/D9 -> 0.96627409 | P13: =G13/G9 -> 1.0462732
A14: OrangeCounty | B14: 1990.1 | C14: 1421 | D14: 18.17 | E14: 49010 | F14: 6.86337 | G14: 128.03333 | H14: 8.423871 | L14: 6.86337 | M14: =F10 -> 7.52181 | N14: 8.423871 | O14: =D14/D10 -> 0.98057205 | P14: =G14/G10 -> 1.0523288
A15: OrangeCounty | B15: 1990.2 | C15: 533 | D15: 18.29 | E15: 49543 | F15: 6.559841 | G15: 129.3 | H15: 8.674127 | L15: 6.559841 | M15: =F11 -> 7.267149 | N15: 8.674127 | O15: =D15/D11 -> 0.99510337 | P15: =G15/G11 -> 1.0458345
A16: OrangeCounty | B16: 1990.3 | C16: 1008 | D16: 18.26 | E16: 50551 | F16: 6.475698 | G16: 131.53333 | H16: 8.7012698 | L16: 6.475698 | M16: =F12 -> 7.065044 | N16: 8.7012698 | O16: =D16/D12 -> 1.0027457 | P16: =G16/G12 -> 1.0556447
A17: OrangeCounty | B17: 1990.4 | C17: 731 | D17: 18.24 | E17: 51282 | F17: 6.619724 | G17: 133.76667 | H17: 8.4059677 | L17: 6.619724 | M17: =F13 -> 7.049333 | N17: 8.4059677 | O17: =D17/D13 -> 1.0105263 | P17: =G17/G13 -> 1.0627648
... A124: OrangeCounty | B124: 2017.3 | C124: 467 | D124: 30.98 | E124: 73254 | F124: 4.252884 | G124: 245.287 | H124: 2.241429 | L124: 4.252884 | M124: =F120 -> 4.679766 | N124: 2.241429 | O124: =D124/D120 -> 1.0839748 | P124: =G124/G120 -> 1.0194494

Sheet Model1 SD
A1: SUMMARY OUTPUT
A3: Regression Statistics
A4: Multiple R | B4: 0.9367461
A5: R Square | B5: 0.87749325
A6: Adjusted R Square | B6: 0.87429742
A7: Standard Error | B7: 0.59248902
A8: Observations | B8: 119
A10: ANOVA
B11: df | C11: SS | D11: MS | E11: F | F11: Significance F
A12: Regression | B12: 3 | C12: 289.16267 | D12: 96.387555 | E12: 274.5746 | F12: 2.9953336e-52
A13: Residual | B13: 115 | C13: 40.369972 | D13: 0.35104324
A14: Total | B14: 118 | C14: 329.53264
B16: Coefficients | C16: Standard Error | D16: t Stat | E16: P-value | F16: Lower 95% | G16: Upper 95% | H16: Lower 95.0% | I16: Upper 95.0%
A17: Intercept | B17: 3.1731828 | C17: 0.8491818 | D17: 3.7367532 | E17: 0.00029186291 | F17: 1.4911171 | G17: 4.8552485 | H17: 1.4911171 | I17: 4.8552485
A18: X Variable 1 | B18: 0.96010877 | C18: 0.043729812 | D18: 21.955475 | E18: 6.1099077e-43 | F18: 0.87348843 | G18: 1.0467291 | H18: 0.87348843 | I18: 1.0467291
A19: X Variable 2 | B19: 0.066533439 | C19: 0.03173503 | D19: 2.0965299 | E19: 0.03822765 | F19: 0.0036724525 | G19: 0.12939443 | H19: 0.0036724525 | I19: 0.12939443
A20: X Variable 3 | B20: -3.2438682 | C20: 0.87689242 | D20: -3.6992773 | E20: 0.00033314368 | F20: -4.9808233 | G20: -1.5069131 | H20: -4.9808233 | I20: -1.5069131
A24: RESIDUAL OUTPUT
A26: Observation | B26: Predicted Y | C26: Residuals
A27: 1 | B27: 7.4954233 | C27: -0.74832925
A28: 2 | B28: 7.2910285 | C28: -0.65519451
A29: 3 | B29: 7.1686987 | C29: -0.8621077
A30: 4 | B30: 7.0654272 | C30: -1.0260222
A31: 5 | B31: 7.0471131 | C31: -1.1067501
A32: 6 | B32: 6.9065628 | C32: -0.52993279
A33: 7 | B33: 6.532776 | C33: 0.10781799
A34: 8 | B34: 6.2484561 | C34: 0.77651888
A35: 9 | B35: 6.245762 | C35: 0.88587696
A36: 10 | B36: 6.7376081 | C36: 0.37270091
A37: 11 | B37: 6.9926049 | C37: 0.1395831
A38: 12 | B38: 7.3417628 | C38: -0.28594284
... A145: 119 | B145: 4.2005654 | C145: 0.24925757

Sheet Model 2 SD
A1: SUMMARY OUTPUT
A3: Regression Statistics
A4: Multiple R | B4: 0.94062231
A5: R Square | B5: 0.88477033
A6: Adjusted R Square | B6: 0.88072718
A7: Standard Error | B7: 0.57713706
A8: Observations | B8: 119
A10: ANOVA
B11: df | C11: SS | D11: MS | E11: F | F11: Significance F
A12: Regression | B12: 4 | C12: 291.5607 | D12: 72.890175 | E12: 218.83212 | F12: 1.6611151e-52
A13: Residual | B13: 114 | C13: 37.971939 | D13: 0.33308718
A14: Total | B14: 118 | C14: 329.53264
B16: Coefficients | C16: Standard Error | D16: t Stat | E16: P-value | F16: Lower 95% | G16: Upper 95% | H16: Lower 95.0% | I16: Upper 95.0%
A17: Intercept | B17: 17.825573 | C17: 5.5231373 | D17: 3.2274362 | E17: 0.0016311089 | F17: 6.8842808 | G17: 28.766866 | H17: 6.8842808 | I17: 28.766866
A18: X Variable 1 | B18: 0.92675316 | C18: 0.044373655 | D18: 20.885211 | E18: 9.041516e-41 | F18: 0.83884929 | G18: 1.014657 | H18: 0.83884929 | I18: 1.014657
A19: X Variable 2 | B19: 0.14196106 | C19: 0.041783319 | D19: 3.3975533 | E19: 0.00093710338 | F19: 0.059188623 | G19: 0.22473349 | H19: 0.059188623 | I19: 0.22473349
A20: X Variable 3 | B20: -2.8622994 | C20: 0.86592824 | D20: -3.3054695 | E20: 0.0012680672 | F20: -4.5776965 | G20: -1.1469022 | H20: -4.5776965 | I20: -1.1469022
A21: X Variable 4 | B21: -14.793387 | C21: 5.5133929 | D21: -2.6831731 | E21: 0.0083780362 | F21: -25.715376 | G21: -3.8713984 | H21: -25.715376 | I21: -3.8713984
A25: RESIDUAL OUTPUT
A27: Observation | B27: Predicted Y | C27: Residuals
A28: 1 | B28: 7.5374311 | C28: -0.79033707
A29: 2 | B29: 7.3752547 | C29: -0.73942071
A30: 3 | B30: 7.2491283 | C30: -0.94253732
A31: 4 | B31: 7.1149572 | C31: -1.0755522
A32: 5 | B32: 7.0627533 | C32: -1.1223903
A33: 6 | B33: 6.8202622 | C33: -0.44363216
A34: 7 | B34: 6.4772926 | C34: 0.16330142
A35: 8 | B35: 6.2000949 | C35: 0.8248801
A36: 9 | B36: 6.1432771 | C36: 0.98836187
A37: 10 | B37: 6.7288941 | C37: 0.3814149
A38: 11 | B38: 6.832035 | C38: 0.300153
A39: 12 | B39: 7.0407958 | C39: 0.015024181
... A146: 119 | B146: 4.1850957 | C146: 0.26472731

Sheet SanDiego
A1: MKT | B1: yearq | C1: COMP | D1: R | E1: STK | F1: CAP | G1: CPI | H1: T10 | L1: CAP | M1: CAP(t-4) | N1: T10 | O1: Rt/Rt-4 | P1: CPIt/CPI(t-4)
A2: SanDiego | B2: 1987.1 | C2: 206 | D2: 18.24 | E2: 24575 | F2: 7.260562 | G2: 111.8 | H2: 7.1954098 | L2: 7.260562 | N2: 7.1954098
A3: SanDiego | B3: 1987.2 | C3: 243 | D3: 18.32 | E3: 24818 | F3: 6.990926 | G3: 113.06667 | H3: 8.3426984 | L3: 6.990926 | N3: 8.3426984
A4: SanDiego | B4: 1987.3 | C4: 283 | D4: 18.2 | E4: 25101 | F4: 6.864758 | G4: 114.26667 | H4: 8.8696875 | L4: 6.864758 | N4: 8.8696875
A5: SanDiego | B5: 1987.4 | C5: 1499 | D5: 18.08 | E5: 26600 | F5: 6.782005 | G5: 115.33333 | H5: 9.1290323 | L5: 6.782005 | N5: 9.1290323
A6: SanDiego | B6: 1988.1 | C6: 942 | D6: 18.04 | E6: 27542 | F6: 6.747094 | G6: 116.23333 | H6: 8.4109677 | L6: 6.747094 | M6: =F2 -> 7.260562 | N6: 8.4109677 | O6: =D6/D2 -> 0.98903509 | P6: =G6/G2 -> 1.0396541
A7: SanDiego | B7: 1988.2 | C7: 288 | D7: 18 | E7: 27830 | F7: 6.635834 | G7: 117.56667 | H7: 8.9128571 | L7: 6.635834 | M7: =F3 -> 6.990926 | N7: 8.9128571 | O7: =D7/D3 -> 0.98253275 | P7: =G7/G3 -> 1.0397995
A8: SanDiego | B8: 1988.3 | C8: 379 | D8: 17.96 | E8: 28209 | F8: 6.306591 | G8: 119 | H8: 9.1035937 | L8: 6.306591 | M8: =F4 -> 6.864758 | N8: 9.1035937 | O8: =D8/D4 -> 0.98681319 | P8: =G8/G4 -> 1.0414236
A9: SanDiego | B9: 1988.4 | C9: 742 | D9: 17.92 | E9: 28951 | F9: 6.039405 | G9: 120.3 | H9: 8.9570492 | L9: 6.039405 | M9: =F5 -> 6.782005 | N9: 8.9570492 | O9: =D9/D5 -> 0.99115044 | P9: =G9/G5 -> 1.0430636
A10: SanDiego | B10: 1989.1 | C10: 538 | D10: 17.89 | E10: 29489 | F10: 5.940363 | G10: 121.66667 | H10: 9.2116393 | L10: 5.940363 | M10: =F6 -> 6.747094 | N10: 9.2116393 | O10: =D10/D6 -> 0.99168514 | P10: =G10/G6 -> 1.0467451
A11: SanDiego | B11: 1989.2 | C11: 1974 | D11: 17.87 | E11: 31463 | F11: 6.37663 | G11: 123.63333 | H11: 8.7579687 | L11: 6.37663 | M11: =F7 -> 6.635834 | N11: 8.7579687 | O11: =D11/D7 -> 0.99277778 | P11: =G11/G7 -> 1.0516019
A12: SanDiego | B12: 1989.3 | C12: 228 | D12: 17.91 | E12: 31691 | F12: 6.640594 | G12: 124.6 | H12: 8.1074603 | L12: 6.640594 | M12: =F8 -> 6.306591 | N12: 8.1074603 | O12: =D12/D8 -> 0.99721604 | P12: =G12/G8 -> 1.0470588
A13: SanDiego | B13: 1989.4 | C13: 821 | D13: 17.95 | E13: 32512 | F13: 7.024975 | G13: 125.86667 | H13: 7.9070968 | L13: 7.024975 | M13: =F9 -> 6.039405 | N13: 7.9070968 | O13: =D13/D9 -> 1.0016741 | P13: =G13/G9 -> 1.0462732
A14: SanDiego | B14: 1990.1 | C14: 1083 | D14: 17.6 | E14: 33595 | F14: 7.131639 | G14: 128.03333 | H14: 8.423871 | L14: 7.131639 | M14: =F10 -> 5.940363 | N14: 8.423871 | O14: =D14/D10 -> 0.98378983 | P14: =G14/G10 -> 1.0523288
A15: SanDiego | B15: 1990.2 | C15: 278 | D15: 17.27 | E15: 33873 | F15: 7.110309 | G15: 129.3 | H15: 8.674127 | L15: 7.110309 | M15: =F11 -> 6.37663 | N15: 8.674127 | O15: =D15/D11 -> 0.96642417 | P15: =G15/G11 -> 1.0458345
A16: SanDiego | B16: 1990.3 | C16: 400 | D16: 17.31 | E16: 34273 | F16: 7.132188 | G16: 131.53333 | H16: 8.7012698 | L16: 7.132188 | M16: =F12 -> 6.640594 | N16: 8.7012698 | O16: =D16/D12 -> 0.96649916 | P16: =G16/G12 -> 1.0556447
A17: SanDiego | B17: 1990.4 | C17: 859 | D17: 17.35 | E17: 35132 | F17: 7.05582 | G17: 133.76667 | H17: 8.4059677 | L17: 7.05582 | M17: =F13 -> 7.024975 | N17: 8.4059677 | O17: =D17/D13 -> 0.96657382 | P17: =G17/G13 -> 1.0627648
... A124: SanDiego | B124: 2017.3 | C124: 247 | D124: 30.66 | E124: 58584 | F124: 4.449823 | G124: 245.287 | H124: 2.241429 | L124: 4.449823 | M124: =F120 -> 4.366569 | N124: 2.241429 | O124: =D124/D120 -> 1.0216594 | P124: =G124/G120 -> 1.0194494

Sheet Model1 San Jose
A1: SUMMARY OUTPUT
A3: Regression Statistics
A4: Multiple R | B4: 0.85805198
A5: R Square | B5: 0.7362532
A6: Adjusted R Square | B6: 0.72937285
A7: Standard Error | B7: 0.83284875
A8: Observations | B8: 119
A10: ANOVA
B11: df | C11: SS | D11: MS | E11: F | F11: Significance F
A12: Regression | B12: 3 | C12: 222.67431 | D12: 74.224771 | E12: 107.00808 | F12: 3.8744142e-33
A13: Residual | B13: 115 | C13: 79.768259 | D13: 0.69363704
A14: Total | B14: 118 | C14: 302.44257
B16: Coefficients | C16: Standard Error | D16: t Stat | E16: P-value | F16: Lower 95% | G16: Upper 95% | H16: Lower 95.0% | I16: Upper 95.0%
A17: Intercept | B17: 5.4454961 | C17: 0.77579694 | D17: 7.0192287 | E17: 1.6574917e-10 | F17: 3.9087917 | G17: 6.9822005 | H17: 3.9087917 | I17: 6.9822005
A18: X Variable 1 | B18: 0.53303837 | C18: 0.061129636 | D18: 8.7198028 | E18: 2.4625611e-14 | F18: 0.41195233 | G18: 0.65412442 | H18: 0.41195233 | I18: 0.65412442
A19: X Variable 2 | B19: 0.29859792 | C19: 0.043451058 | D19: 6.8720517 | E19: 3.4541409e-10 | F19: 0.21252974 | G19: 0.3846661 | H19: 0.21252974 | I19: 0.3846661
A20: X Variable 3 | B20: -3.3658032 | C20: 0.57045568 | D20: -5.900201 | E20: 3.7340329e-08 | F20: -4.4957661 | G20: -2.2358403 | H20: -4.4957661 | I20: -2.2358403
A24: RESIDUAL OUTPUT
A26: Observation | B26: Predicted Y | C26: Residuals
A27: 1 | B27: 8.745965 | C27: -1.082567
A28: 2 | B28: 8.9112369 | C28: -1.1511799
A29: 3 | B29: 8.8409176 | C29: -1.0057756
A30: 4 | B30: 8.6875463 | C30: -0.8654133
A31: 5 | B31: 8.6459699 | C31: -0.88413893
A32: 6 | B32: 8.4043894 | C32: -0.65717841
A33: 7 | B33: 8.3907939 | C33: -0.62786492
A34: 8 | B34: 8.4590455 | C34: -0.65214045
A35: 9 | B35: 8.5846931 | C35: -0.74545907
A36: 10 | B36: 8.6550297 | C36: -0.58171165
A37: 11 | B37: 8.620694 | C37: -0.27511797
A38: 12 | B38: 8.5069164 | C38: 0.1387856
... A145: 119 | B145: 5.1656973 | C145: -0.43452226

Sheet Model 2 San Jose
A1: SUMMARY OUTPUT
A3: Regression Statistics
A4: Multiple R | B4: 0.86628854
A5: R Square | B5: 0.75045583
A6: Adjusted R Square | B6: 0.74169989
A7: Standard Error | B7: 0.8136596
A8: Observations | B8: 119
A10: ANOVA
B11: df | C11: SS | D11: MS | E11: F | F11: Significance F
A12: Regression | B12: 4 | C12: 226.96979 | D12: 56.742447 | E12: 85.708237 | F12: 1.8995012e-33
A13: Residual | B13: 114 | C13: 75.472781 | D13: 0.66204194
A14: Total | B14: 118 | C14: 302.44257
B16: Coefficients | C16: Standard Error | D16: t Stat | E16: P-value | F16: Lower 95% | G16: Upper 95% | H16: Lower 95.0% | I16: Upper 95.0%
A17: Intercept | B17: 24.488672 | C17: 7.5144421 | D17: 3.2588809 | E17: 0.001474489 | F17: 9.6026197 | G17: 39.374724 | H17: 9.6026197 | I17: 39.374724
A18: X Variable 1 | B18: 0.54323673 | C18: 0.059855243 | D18: 9.0758421 | E18: 3.9294121e-15 | F18: 0.42466396 | G18: 0.66180951 | H18: 0.42466396 | I18: 0.66180951
A19: X Variable 2 | B19: 0.37328242 | C19: 0.051591402 | D19: 7.235361 | E19: 5.7675183e-11 | F19: 0.27108025 | G19: 0.47548459 | H19: 0.27108025 | I19: 0.47548459
A20: X Variable 3 | B20: -3.1460713 | C20: 0.56394888 | D20: -5.5786463 | E20: 1.6557227e-07 | F20: -4.2632497 | G20: -2.0288929 | H20: -4.2632497 | I20: -2.0288929
A21: X Variable 4 | B21: -19.215393 | C21: 7.5437319 | D21: -2.5471998 | E21: 0.012191382 | F21: -34.159467 | G21: -4.2713177 | H21: -34.159467 | I21: -4.2713177
A25: RESIDUAL OUTPUT
A27: Observation | B27: Predicted Y | C27: Residuals
A28: 1 | B28: 8.7273919 | C28: -1.0639939
A29: 2 | B29: 8.9274304 | C29: -1.1673734
A30: 3 | B30: 8.8483929 | C30: -1.0132509
A31: 4 | B31: 8.6616897 | C31: -0.83955668
A32: 5 | B32: 8.5789543 | C32: -0.81712329
A33: 6 | B33: 8.2214418 | C33: -0.47423083
A34: 7 | B34: 8.2381464 | C34: -0.47521741
A35: 8 | B35: 8.297583 | C35: -0.49067798
A36: 9 | B36: 8.3446232 | C36: -0.50538925
A37: 10 | B37: 8.5580695 | C37: -0.4847515
A38: 11 | B38: 8.3407306 | C38: 0.004845353
A39: 12 | B39: 8.0717332 | C39: 0.57396883
... A146: 119 | B146: 5.0611258 | C146: -0.32995082

Sheet SanJose
A1: MKT | B1: yearq | C1: COMP | D1: R | E1: STK | F1: CAP | G1: CPI | H1: T10 | L1: CAP | M1: CAP(t-4) | N1: T10 | O1: Rt/Rt-4 | P1: CPIt/CPI(t-4)
A2: SanJose | B2: 1987.1 | C2: 477 | D2: 17.61 | E2: 20766 | F2: 7.532759 | G2: 111.8 | H2: 7.1954098 | L2: 7.532759 | N2: 7.1954098
A3: SanJose | B3: 1987.2 | C3: 71 | D3: 17.29 | E3: 20837 | F3: 7.556822 | G3: 113.06667 | H3: 8.3426984 | L3: 7.556822 | N3: 8.3426984
A4: SanJose | B4: 1987.3 | C4: 0 | D4: 17.25 | E4: 20837 | F4: 7.555368 | G4: 114.26667 | H4: 8.8696875 | L4: 7.555368 | N4: 8.8696875
A5: SanJose | B5: 1987.4 | C5: 1262 | D5: 17.21 | E5: 22099 | F5: 7.599154 | G5: 115.33333 | H5: 9.1290323 | L5: 7.599154 | N5: 9.1290323
A6: SanJose | B6: 1988.1 | C6: 227 | D6: 16.88 | E6: 22326 | F6: 7.663398 | G6: 116.23333 | H6: 8.4109677 | L6: 7.663398 | M6: =F2 -> 7.532759 | N6: 8.4109677 | O6: =D6/D2 -> 0.95854628 | P6: =G6/G2 -> 1.0396541
A7: SanJose | B7: 1988.2 | C7: 500 | D7: 16.56 | E7: 22826 | F7: 7.760057 | G7: 117.56667 | H7: 8.9128571 | L7: 7.760057 | M7: =F3 -> 7.556822 | N7: 8.9128571 | O7: =D7/D3 -> 0.95777906 | P7: =G7/G3 -> 1.0397995
A8: SanJose | B8: 1988.3 | C8: 0 | D8: 17.17 | E8: 22826 | F8: 7.835142 | G8: 119 | H8: 9.1035937 | L8: 7.835142 | M8: =F4 -> 7.555368 | N8: 9.1035937 | O8: =D8/D4 -> 0.99536232 | P8: =G8/G4 -> 1.0414236
A9: SanJose | B9: 1988.4 | C9: 155 | D9: 17.81 | E9: 22981 | F9: 7.822133 | G9: 120.3 | H9: 8.9570492 | L9: 7.822133 | M9: =F5 -> 7.599154 | N9: 8.9570492 | O9: =D9/D5 -> 1.0348635 | P9: =G9/G5 -> 1.0430636
A10: SanJose | B10: 1989.1 | C10: 408 | D10: 18.23 | E10: 23389 | F10: 7.761831 | G10: 121.66667 | H10: 9.2116393 | L10: 7.761831 | M10: =F6 -> 7.663398 | N10: 9.2116393 | O10: =D10/D6 -> 1.0799763 | P10: =G10/G6 -> 1.0467451
A11: SanJose | B11: 1989.2 | C11: 21 | D11: 18.66 | E11: 23410 | F11: 7.747211 | G11: 123.63333 | H11: 8.7579687 | L11: 7.747211 | M11: =F7 -> 7.760057 | N11: 8.7579687 | O11: =D11/D7 -> 1.1268116 | P11: =G11/G7 -> 1.0516019
A12: SanJose | B12: 1989.3 | C12: 117 | D12: 18.63 | E12: 23527 | F12: 7.762929 | G12: 124.6 | H12: 8.1074603 | L12: 7.762929 | M12: =F8 -> 7.835142 | N12: 8.1074603 | O12: =D12/D8 -> 1.085032 | P12: =G12/G8 -> 1.0470588
A13: SanJose | B13: 1989.4 | C13: 104 | D13: 18.61 | E13: 23631 | F13: 7.806905 | G13: 125.86667 | H13: 7.9070968 | L13: 7.806905 | M13: =F9 -> 7.822133 | N13: 7.9070968 | O13: =D13/D9 -> 1.0449186 | P13: =G13/G9 -> 1.0462732
A14: SanJose | B14: 1990.1 | C14: 45 | D14: 19.03 | E14: 23676 | F14: 7.839234 | G14: 128.03333 | H14: 8.423871 | L14: 7.839234 | M14: =F10 -> 7.761831 | N14: 8.423871 | O14: =D14/D10 -> 1.0438837 | P14: =G14/G10 -> 1.0523288
A15: SanJose | B15: 1990.2 | C15: 54 | D15: 19.46 | E15: 23730 | F15: 8.073318 | G15: 129.3 | H15: 8.674127 | L15: 8.073318 | M15: =F11 -> 7.747211 | N15: 8.674127 | O15: =D15/D11 -> 1.0428725 | P15: =G15/G11 -> 1.0458345
A16: SanJose | B16: 1990.3 | C16: 27 | D16: 19.71 | E16: 23757 | F16: 8.345576 | G16: 131.53333 | H16: 8.7012698 | L16: 8.345576 | M16: =F12 -> 7.762929 | N16: 8.7012698 | O16: =D16/D12 -> 1.057971 | P16: =G16/G12 -> 1.0556447
A17: SanJose | B17: 1990.4 | C17: 156 | D17: 19.96 | E17: 23913 | F17: 8.645702 | G17: 133.76667 | H17: 8.4059677 | L17: 8.645702 | M17: =F13 -> 7.806905 | N17: 8.4059677 | O17: =D17/D13 -> 1.0725416 | P17: =G17/G13 -> 1.0627648
... A124: SanJose | B124: 2017.3 | C124: 1126 | D124: 36.5 | E124: 49002 | F124: 4.731175 | G124: 245.287 | H124: 2.241429 | L124: 4.731175 | M124: =F120 -> 4.711724 | N124: 2.241429 | O124: =D124/D120 -> 1.028169 | P124: =G124/G120 -> 1.0194494

Sheet Model 1 Summary
A1: Model 1 Summary: CAP = β + α₁CAP(t-4) + α₂T10 + α₃(Rt/Rt-4)
B3: Regression Statistics | F3: Coefficients | J3: P-values
A4: City | B4: R² | C4: Adj R² | D4: Std Error | E4: Obs | F4: Intercept (β) | G4: CAP(t-4) (α₁) | H4: T10 (α₂) | I4: Rt/Rt-4 (α₃) | J4: Intercept | K4: CAP(t-4) | L4: T10 | M4: Rt/Rt-4
A5: Atlanta | B5: ='Model 1 ATL'!B5 -> 0.5209565 | C5: ='Model 1 ATL'!B6 -> 0.50845971 | D5: ='Model 1 ATL'!B7 -> 0.96119497 | E5: ='Model 1 ATL'!B8 -> 119 | F5: ='Model 1 ATL'!B17 -> 3.5751792 | G5: ='Model 1 ATL'!B18 -> 0.71464442 | H5: ='Model 1 ATL'!B19 -> 0.074887428 | I5: ='Model 1 ATL'!B20 -> -1.9126115 | J5: ='Model 1 ATL'!E17 -> 0.067680789 | K5: ='Model 1 ATL'!E18 -> 6.6078277e-18 | L5: ='Model 1 ATL'!E19 -> 0.087805294 | M5: ='Model 1 ATL'!E20 -> 0.30688088
A6: Boston | B6: ='Model1 Bos'!B5 -> 0.72841355 | C6: ='Model1 Bos'!B6 -> 0.72132869 | D6: ='Model1 Bos'!B7 -> 0.91712387 | E6: ='Model1 Bos'!B8 -> 119 | F6: ='Model1 Bos'!B17 -> 2.9797851 | G6: ='Model1 Bos'!B18 -> 0.84455618 | H6: ='Model1 Bos'!B19 -> 0.067168611 | I6: ='Model1 Bos'!B20 -> -2.2963517 | J6: ='Model1 Bos'!E17 -> 0.00059020637 | K6: ='Model1 Bos'!E18 -> 5.8093207e-27 | L6: ='Model1 Bos'!E19 -> 0.15326938 | M6: ='Model1 Bos'!E20 -> 0.0028185317
A7: Chicago | B7: ='Model 1 Chi'!B5 -> 0.69018211 | C7: ='Model 1 Chi'!B6 -> 0.68209991 | D7: ='Model 1 Chi'!B7 -> 0.70102627 | E7: ='Model 1 Chi'!B8 -> 119 | F7: ='Model 1 Chi'!B17 -> 4.4476367 | G7: ='Model 1 Chi'!B18 -> 0.81966888 | H7: ='Model 1 Chi'!B19 -> 0.083104673 | I7: ='Model 1 Chi'!B20 -> -3.613375 | J7: ='Model 1 Chi'!E17 -> 0.0016929447 | K7: ='Model 1 Chi'!E18 -> 5.7700802e-27 | L7: ='Model 1 Chi'!E19 -> 0.012865417 | M7: ='Model 1 Chi'!E20 -> 0.010159341
A8: Dallas | B8: ='Model1 Dallas'!B5 -> 0.80144665 | C8: ='Model1 Dallas'!B6 -> 0.79626699 | D8: ='Model1 Dallas'!B7 -> 0.81013697 | E8: ='Model1 Dallas'!B8 -> 119 | F8: ='Model1 Dallas'!B17 -> 2.0865651 | G8: ='Model1 Dallas'!B18 -> 0.8378277 | H8: ='Model1 Dallas'!B19 -> 0.161694 | I8: ='Model1 Dallas'!B20 -> -1.6451235 | J8: ='Model1 Dallas'!E17 -> 0.043157485 | K8: ='Model1 Dallas'!E18 -> 3.738467e-39 | L8: ='Model1 Dallas'!E19 -> 1.7097451e-05 | M8: ='Model1 Dallas'!E20 -> 0.096379504
A9: NewYork | B9: ='Model1 NY'!B5 -> 0.81302786 | C9: ='Model1 NY'!B6 -> 0.80815033 | D9: ='Model1 NY'!B7 -> 0.73478161 | E9: ='Model1 NY'!B8 -> 119 | F9: ='Model1 NY'!B17 -> 4.1982003 | G9: ='Model1 NY'!B18 -> 0.80544029 | H9: ='Model1 NY'!B19 -> 0.12301428 | I9: ='Model1 NY'!B20 -> -3.5382127 | J9: ='Model1 NY'!E17 -> 2.2030367e-06 | K9: ='Model1 NY'!E18 -> 2.1028449e-28 | L9: ='Model1 NY'!E19 -> 0.0034495787 | M9: ='Model1 NY'!E20 -> 6.8724186e-06
A10: OrangeCounty | B10: ='Model1 OC'!B5 -> 0.86509296 | C10: ='Model1 OC'!B6 -> 0.86157365 | D10: ='Model1 OC'!B7 -> 0.58152413 | E10: ='Model1 OC'!B8 -> 119 | F10: ='Model1 OC'!B17 -> 4.438903 | G10: ='Model1 OC'!B18 -> 0.91606645 | H10: ='Model1 OC'!B19 -> 0.041569462 | I10: ='Model1 OC'!B20 -> -4.1194908 | J10: ='Model1 OC'!E17 -> 6.5950646e-08 | K10: ='Model1 OC'!E18 -> 7.503398e-36 | L10: ='Model1 OC'!E19 -> 0.25158724 | M10: ='Model1 OC'!E20 -> 2.6011128e-07
A11: SanDiego | B11: ='Model1 SD'!B5 -> 0.87749325 | C11: ='Model1 SD'!B6 -> 0.87429742 | D11: ='Model1 SD'!B7 -> 0.59248902 | E11: ='Model1 SD'!B8 -> 119 | F11: ='Model1 SD'!B17 -> 3.1731828 | G11: ='Model1 SD'!B18 -> 0.96010877 | H11: ='Model1 SD'!B19 -> 0.066533439 | I11: ='Model1 SD'!B20 -> -3.2438682 | J11: ='Model1 SD'!E17 -> 0.00029186291 | K11: ='Model1 SD'!E18 -> 6.1099077e-43 | L11: ='Model1 SD'!E19 -> 0.03822765 | M11: ='Model1 SD'!E20 -> 0.00033314368
A12: SanJose | B12: ='Model1 San Jose'!B5 -> 0.7362532 | C12: ='Model1 San Jose'!B6 -> 0.72937285 | D12: ='Model1 San Jose'!B7 -> 0.83284875 | E12: ='Model1 San Jose'!B8 -> 119 | F12: ='Model1 San Jose'!B17 -> 5.4454961 | G12: ='Model1 San Jose'!B18 -> 0.53303837 | H12: ='Model1 San Jose'!B19 -> 0.29859792 | I12: ='Model1 San Jose'!B20 -> -3.3658032 | J12: ='Model1 San Jose'!E17 -> 1.6574917e-10 | K12: ='Model1 San Jose'!E18 -> 2.4625611e-14 | L12: ='Model1 San Jose'!E19 -> 3.4541409e-10 | M12: ='Model1 San Jose'!E20 -> 3.7340329e-08

Sheet Model 2 Summary
A1: Model 2 Summary: CAP = β + α₁CAP(t-4) + α₂T10 + α₃(Rt/Rt-4) + α₄(CPIt/CPIt-4)
B3: Regression Statistics | F3: Coefficients | K3: P-values
A4: City | B4: R² | C4: Adj R² | D4: Std Error | E4: Obs | F4: Intercept (β) | G4: CAP(t-4) (α₁) | H4: T10 (α₂) | I4: Rt/Rt-4 (α₃) | J4: CPIt/CPIt-4 (α₄) | K4: Intercept | L4: CAP(t-4) | M4: T10 | N4: Rt/Rt-4 | O4: CPIt/CPIt-4
A5: Atlanta | B5: ='Model 2 ATL'!B5 -> 0.61330753 | C5: ='Model 2 ATL'!B6 -> 0.59973937 | D5: ='Model 2 ATL'!B7 -> 0.86736794 | E5: ='Model 2 ATL'!B8 -> 119 | F5: ='Model 2 ATL'!B17 -> 47.123533 | G5: ='Model 2 ATL'!B18 -> 0.68744746 | H5: ='Model 2 ATL'!B19 -> 0.25341247 | I5: ='Model 2 ATL'!B20 -> -3.0632231 | J5: ='Model 2 ATL'!B21 -> -41.969148 | K5: ='Model 2 ATL'!E17 -> 2.0971044e-07 | L5: ='Model 2 ATL'!E18 -> 2.3113174e-19 | M5: ='Model 2 ATL'!E19 -> 3.6727759e-06 | N5: ='Model 2 ATL'!E20 -> 0.07353392 | O5: ='Model 2 ATL'!E21 -> 8.2033629e-07
A6: Boston | B6: ='Model 2 Bos'!B5 -> 0.76958119 | C6: ='Model 2 Bos'!B6 -> 0.76149632 | D6: ='Model 2 Bos'!B7 -> 0.84845617 | E6: ='Model 2 Bos'!B8 -> 119 | F6: ='Model 2 Bos'!B17 -> 38.284174 | G6: ='Model 2 Bos'!B18 -> 0.82652172 | H6: ='Model 2 Bos'!B19 -> 0.2208476 | I6: ='Model 2 Bos'!B20 -> -2.088515 | J6: ='Model 2 Bos'!B21 -> -35.230574 | K6: ='Model 2 Bos'!E17 -> 3.6279364e-06 | L6: ='Model 2 Bos'!E18 -> 1.2995747e-28 | M6: ='Model 2 Bos'!E19 -> 0.00010742096 | N6: ='Model 2 Bos'!E20 -> 0.0033726989 | O6: ='Model 2 Bos'!E21 -> 1.563359e-05
A7: Chicago | B7: ='Model 2 Chi'!B5 -> 0.72986186 | C7: ='Model 2 Chi'!B6 -> 0.72038333 | D7: ='Model 2 Chi'!B7 -> 0.65746175 | E7: ='Model 2 Chi'!B8 -> 119 | F7: ='Model 2 Chi'!B17 -> 30.595863 | G7: ='Model 2 Chi'!B18 -> 0.78059757 | H7: ='Model 2 Chi'!B19 -> 0.19734729 | I7: ='Model 2 Chi'!B20 -> -4.1674382 | J7: ='Model 2 Chi'!B21 -> -25.217827 | K7: ='Model 2 Chi'!E17 -> 7.5656025e-06 | L7: ='Model 2 Chi'!E18 -> 6.9387677e-27 | M7: ='Model 2 Chi'!E19 -> 6.1283598e-06 | N7: ='Model 2 Chi'!E20 -> 0.0017994548 | O7: ='Model 2 Chi'!E21 -> 8.0086589e-05
A8: Dallas | B8: ='Model 2 DAL'!B5 -> 0.81021525 | C8: ='Model 2 DAL'!B6 -> 0.80355614 | D8: ='Model 2 DAL'!B7 -> 0.79551247 | E8: ='Model 2 DAL'!B8 -> 119 | F8: ='Model 2 DAL'!B17 -> 19.56788 | G8: ='Model 2 DAL'!B18 -> 0.81185704 | H8: ='Model 2 DAL'!B19 -> 0.23735651 | I8: ='Model 2 DAL'!B20 -> -1.5187948 | J8: ='Model 2 DAL'!B21 -> -17.343633 | K8: ='Model 2 DAL'!E17 -> 0.012197557 | L8: ='Model 2 DAL'!E18 -> 4.1993641e-37 | M8: ='Model 2 DAL'!E19 -> 3.0795212e-06 | N8: ='Model 2 DAL'!E20 -> 0.11836475 | O8: ='Model 2 DAL'!E21 -> 0.023561504
A9: NewYork | B9: ='Model 2 NY'!B5 -> 0.83354769 | C9: ='Model 2 NY'!B6 -> 0.82770726 | D9: ='Model 2 NY'!B7 -> 0.69632379 | E9: ='Model 2 NY'!B8 -> 119 | F9: ='Model 2 NY'!B17 -> 29.253255 | G9: ='Model 2 NY'!B18 -> 0.77762865 | H9: ='Model 2 NY'!B19 -> 0.24424366 | I9: ='Model 2 NY'!B20 -> -2.5508964 | J9: ='Model 2 NY'!B21 -> -25.804413 | K9: ='Model 2 NY'!E17 -> 3.0248639e-05 | L9: ='Model 2 NY'!E18 -> 1.3772434e-28 | M9: ='Model 2 NY'!E19 -> 4.4966843e-06 | N9: ='Model 2 NY'!E20 -> 0.0010502864 | O9: ='Model 2 NY'!E21 -> 0.00028067377
A10: OrangeCounty | B10: ='Model 2 OC'!B5 -> 0.87203109 | C10: ='Model 2 OC'!B6 -> 0.86754095 | D10: ='Model 2 OC'!B7 -> 0.56885185 | E10: ='Model 2 OC'!B8 -> 119 | F10: ='Model 2 OC'!B17 -> 17.845047 | G10: ='Model 2 OC'!B18 -> 0.88508728 | H10: ='Model 2 OC'!B19 -> 0.11294398 | I10: ='Model 2 OC'!B20 -> -3.9468343 | J10: ='Model 2 OC'!B21 -> -13.374113 | K10: ='Model 2 OC'!E17 -> 0.0013880042 | L10: ='Model 2 OC'!E18 -> 4.1082718e-34 | M10: ='Model 2 OC'!E19 -> 0.014494952 | N10: ='Model 2 OC'!E20 -> 4.8289172e-07 | O10: ='Model 2 OC'!E21 -> 0.014364289
A11: SanDiego | B11: ='Model 2 SD'!B5 -> 0.88477033 | C11: ='Model 2 SD'!B6 -> 0.88072718 | D11: ='Model 2 SD'!B7 -> 0.57713706 | E11: ='Model 2 SD'!B8 -> 119 | F11: ='Model 2 SD'!B17 -> 17.825573 | G11: ='Model 2 SD'!B18 -> 0.92675316 | H11: ='Model 2 SD'!B19 -> 0.14196106 | I11: ='Model 2 SD'!B20 -> -2.8622994 | J11: ='Model 2 SD'!B21 -> -14.793387 | K11: ='Model 2 SD'!E17 -> 0.0016311089 | L11: ='Model 2 SD'!E18 -> 9.041516e-41 | M11: ='Model 2 SD'!E19 -> 0.00093710338 | N11: ='Model 2 SD'!E20 -> 0.0012680672 | O11: ='Model 2 SD'!E21 -> 0.0083780362
A12: SanJose | B12: ='Model 2 San Jose'!B5 -> 0.75045583 | C12: ='Model 2 San Jose'!B6 -> 0.74169989 | D12: ='Model 2 San Jose'!B7 -> 0.8136596 | E12: ='Model 2 San Jose'!B8 -> 119 | F12: ='Model 2 San Jose'!B17 -> 24.488672 | G12: ='Model 2 San Jose'!B18 -> 0.54323673 | H12: ='Model 2 San Jose'!B19 -> 0.37328242 | I12: ='Model 2 San Jose'!B20 -> -3.1460713 | J12: ='Model 2 San Jose'!B21 -> -19.215393 | K12: ='Model 2 San Jose'!E17 -> 0.001474489 | L12: ='Model 2 San Jose'!E18 -> 3.9294121e-15 | M12: ='Model 2 San Jose'!E19 -> 5.7675183e-11 | N12: ='Model 2 San Jose'!E20 -> 1.6557227e-07 | O12: ='Model 2 San Jose'!E21 -> 0.012191382

Sheet Rt Coefficient Comparison
A1: Rt/Rt-4 Coefficient Comparison: Model 1 vs Model 2
B3: Model 1 | D3: Model 2
A4: City | B4: Coefficient (α₃) | C4: P-value | D4: Coefficient (α₃) | E4: P-value | F4: Change
A5: Atlanta | B5: ='Model 1 ATL'!B20 -> -1.9126115 | C5: ='Model 1 ATL'!E20 -> 0.30688088 | D5: ='Model 2 ATL'!B20 -> -3.0632231 | E5: ='Model 2 ATL'!E20 -> 0.07353392 | F5: =D5-B5 -> -1.1506116
A6: Boston | B6: ='Model1 Bos'!B20 -> -2.2963517 | C6: ='Model1 Bos'!E20 -> 0.0028185317 | D6: ='Model 2 Bos'!B20 -> -2.088515 | E6: ='Model 2 Bos'!E20 -> 0.0033726989 | F6: =D6-B6 -> 0.20783669
A7: Chicago | B7: ='Model 1 Chi'!B20 -> -3.613375 | C7: ='Model 1 Chi'!E20 -> 0.010159341 | D7: ='Model 2 Chi'!B20 -> -4.1674382 | E7: ='Model 2 Chi'!E20 -> 0.0017994548 | F7: =D7-B7 -> -0.55406318
A8: Dallas | B8: ='Model1 Dallas'!B20 -> -1.6451235 | C8: ='Model1 Dallas'!E20 -> 0.096379504 | D8: ='Model 2 DAL'!B20 -> -1.5187948 | E8: ='Model 2 DAL'!E20 -> 0.11836475 | F8: =D8-B8 -> 0.12632874
A9: NewYork | B9: ='Model1 NY'!B20 -> -3.5382127 | C9: ='Model1 NY'!E20 -> 6.8724186e-06 | D9: ='Model 2 NY'!B20 -> -2.5508964 | E9: ='Model 2 NY'!E20 -> 0.0010502864 | F9: =D9-B9 -> 0.98731636
A10: OrangeCounty | B10: ='Model1 OC'!B20 -> -4.1194908 | C10: ='Model1 OC'!E20 -> 2.6011128e-07 | D10: ='Model 2 OC'!B20 -> -3.9468343 | E10: ='Model 2 OC'!E20 -> 4.8289172e-07 | F10: =D10-B10 -> 0.17265652
A11: SanDiego | B11: ='Model1 SD'!B20 -> -3.2438682 | C11: ='Model1 SD'!E20 -> 0.00033314368 | D11: ='Model 2 SD'!B20 -> -2.8622994 | E11: ='Model 2 SD'!E20 -> 0.0012680672 | F11: =D11-B11 -> 0.38156882
A12: SanJose | B12: ='Model1 San Jose'!B20 -> -3.3658032 | C12: ='Model1 San Jose'!E20 -> 3.7340329e-08 | D12: ='Model 2 San Jose'!B20 -> -3.1460713 | E12: ='Model 2 San Jose'!E20 -> 1.6557227e-07 | F12: =D12-B12 -> 0.21973186
A14: Model 1: CAP = β + α₁CAP(t-4) + α₂T10 + α₃(Rt/Rt-4)
A15: Model 2: CAP = β + α₁CAP(t-4) + α₂T10 + α₃(Rt/Rt-4) + α₄(CPIt/CPIt-4)
A16: Note: In Model 2, the rent growth coefficient represents REAL rent growth (controlling for inflation)

Sheet Long Run T10 Coefficient
A1: Long Run Coefficient on T10 (Model 2)
A2: Formula: Long Run T10 = α₂ / (1 - α₁)
A4: City | B4: α₁ (CAP t-4) | C4: α₂ (T10) | D4: 1 - α₁ | E4: Long Run T10
A5: Atlanta | B5: ='Model 2 ATL'!B18 -> 0.68744746 | C5: ='Model 2 ATL'!B19 -> 0.25341247 | D5: =1-B5 -> 0.31255254 | E5: =C5/D5 -> 0.81078357
A6: Boston | B6: ='Model 2 Bos'!B18 -> 0.82652172 | C6: ='Model 2 Bos'!B19 -> 0.2208476 | D6: =1-B6 -> 0.17347828 | E6: =C6/D6 -> 1.2730562
A7: Chicago | B7: ='Model 2 Chi'!B18 -> 0.78059757 | C7: ='Model 2 Chi'!B19 -> 0.19734729 | D7: =1-B7 -> 0.21940243 | E7: =C7/D7 -> 0.89947634
A8: Dallas | B8: ='Model 2 DAL'!B18 -> 0.81185704 | C8: ='Model 2 DAL'!B19 -> 0.23735651 | D8: =1-B8 -> 0.18814296 | E8: =C8/D8 -> 1.2615753
A9: NewYork | B9: ='Model 2 NY'!B18 -> 0.77762865 | C9: ='Model 2 NY'!B19 -> 0.24424366 | D9: =1-B9 -> 0.22237135 | E9: =C9/D9 -> 1.0983594
A10: OrangeCounty | B10: ='Model 2 OC'!B18 -> 0.88508728 | C10: ='Model 2 OC'!B19 -> 0.11294398 | D10: =1-B10 -> 0.11491272 | E10: =C10/D10 -> 0.98286757
A11: SanDiego | B11: ='Model 2 SD'!B18 -> 0.92675316 | C11: ='Model 2 SD'!B19 -> 0.14196106 | D11: =1-B11 -> 0.073246839 | E11: =C11/D11 -> 1.9381185
A12: SanJose | B12: ='Model 2 San Jose'!B18 -> 0.54323673 | C12: ='Model 2 San Jose'!B19 -> 0.37328242 | D12: =1-B12 -> 0.45676327 | E12: =C12/D12 -> 0.81723388
A14: Average | E14: =AVERAGE(E5:E12) -> 1.1351838
A16: Note: In the Gordon Growth Formula, the long-run coefficient on T10 should be near 1.
A17: This represents the full pass-through of interest rate changes to cap rates in equilibrium.

Sheet T10 vs Avg Growth Comparison
A1: Model 2: T10 Coefficient vs Average of Rent Growth & Inflation Coefficients
A2: Per GGF theory: CAP = r - g, so coefficient on T10 should equal (opposite sign of) average of growth coefficients
A4: City | B4: α₂ (T10) | C4: α₃ (Rt/Rt-4) | D4: α₄ (CPIt/CPIt-4) | E4: Avg of α₃ & α₄ | F4: Avg (abs value) | G4: Difference
A5: Atlanta | B5: ='Model 2 ATL'!B19 -> 0.25341247 | C5: ='Model 2 ATL'!B20 -> -3.0632231 | D5: ='Model 2 ATL'!B21 -> -41.969148 | E5: =(C5+D5)/2 -> -22.516186 | F5: =ABS(E5) -> 22.516186 | G5: =B5-F5 -> -22.262773
A6: Boston | B6: ='Model 2 Bos'!B19 -> 0.2208476 | C6: ='Model 2 Bos'!B20 -> -2.088515 | D6: ='Model 2 Bos'!B21 -> -35.230574 | E6: =(C6+D6)/2 -> -18.659545 | F6: =ABS(E6) -> 18.659545 | G6: =B6-F6 -> -18.438697
A7: Chicago | B7: ='Model 2 Chi'!B19 -> 0.19734729 | C7: ='Model 2 Chi'!B20 -> -4.1674382 | D7: ='Model 2 Chi'!B21 -> -25.217827 | E7: =(C7+D7)/2 -> -14.692633 | F7: =ABS(E7) -> 14.692633 | G7: =B7-F7 -> -14.495285
A8: Dallas | B8: ='Model 2 DAL'!B19 -> 0.23735651 | C8: ='Model 2 DAL'!B20 -> -1.5187948 | D8: ='Model 2 DAL'!B21 -> -17.343633 | E8: =(C8+D8)/2 -> -9.4312139 | F8: =ABS(E8) -> 9.4312139 | G8: =B8-F8 -> -9.1938574
A9: NewYork | B9: ='Model 2 NY'!B19 -> 0.24424366 | C9: ='Model 2 NY'!B20 -> -2.5508964 | D9: ='Model 2 NY'!B21 -> -25.804413 | E9: =(C9+D9)/2 -> -14.177655 | F9: =ABS(E9) -> 14.177655 | G9: =B9-F9 -> -13.933411
A10: OrangeCounty | B10: ='Model 2 OC'!B19 -> 0.11294398 | C10: ='Model 2 OC'!B20 -> -3.9468343 | D10: ='Model 2 OC'!B21 -> -13.374113 | E10: =(C10+D10)/2 -> -8.6604736 | F10: =ABS(E10) -> 8.6604736 | G10: =B10-F10 -> -8.5475296
A11: SanDiego | B11: ='Model 2 SD'!B19 -> 0.14196106 | C11: ='Model 2 SD'!B20 -> -2.8622994 | D11: ='Model 2 SD'!B21 -> -14.793387 | E11: =(C11+D11)/2 -> -8.8278433 | F11: =ABS(E11) -> 8.8278433 | G11: =B11-F11 -> -8.6858822
A12: SanJose | B12: ='Model 2 San Jose'!B19 -> 0.37328242 | C12: ='Model 2 San Jose'!B20 -> -3.1460713 | D12: ='Model 2 San Jose'!B21 -> -19.215393 | E12: =(C12+D12)/2 -> -11.180732 | F12: =ABS(E12) -> 11.180732 | G12: =B12-F12 -> -10.80745
A14: Average | B14: =AVERAGE(B5:B12) -> 0.22267437 | C14: =AVERAGE(C5:C12) -> -2.918009 | D14: =AVERAGE(D5:D12) -> -24.118561 | E14: =AVERAGE(E5:E12) -> -13.518285 | F14: =AVERAGE(F5:F12) -> 13.518285 | G14: =AVERAGE(G5:G12) -> -13.295611

Sheet Residual Analysis (Last 2 Yrs)
A1: Residual Analysis: Last 2 Years (2015.4 - 2017.3)
A2: Residual = Actual CAP - Predicted CAP | Positive = Undervalued (buy signal) | Negative = Overvalued (sell signal)
A4: City | B4: 2015.4 | C4: 2016.1 | D4: 2016.2 | E4: 2016.3 | F4: 2016.4 | G4: 2017.1 | H4: 2017.2 | I4: 2017.3 | J4: Avg Residual | K4: Interpretation
A5: Atlanta | B5: ='Model 2 ATL'!C138 -> -0.83186854 | C5: ='Model 2 ATL'!C139 -> -1.3267225 | D5: ='Model 2 ATL'!C140 -> -1.1060326 | E5: ='Model 2 ATL'!C141 -> -0.98822096 | F5: ='Model 2 ATL'!C142 -> -0.55749668 | G5: ='Model 2 ATL'!C143 -> -0.37686945 | H5: ='Model 2 ATL'!C144 -> -0.043237817 | I5: ='Model 2 ATL'!C145 -> -0.18358203 | J5: =AVERAGE(B5:I5) -> -0.67675382 | K5: =IF(J5>0,"Undervalued","Overvalued") -> Overvalued
A6: Boston | B6: ='Model 2 Bos'!C138 -> -0.80811186 | C6: ='Model 2 Bos'!C139 -> -0.74569013 | D6: ='Model 2 Bos'!C140 -> -0.55118532 | E6: ='Model 2 Bos'!C141 -> -0.66202301 | F6: ='Model 2 Bos'!C142 -> -0.63130954 | G6: ='Model 2 Bos'!C143 -> -0.41442198 | H6: ='Model 2 Bos'!C144 -> -0.075487639 | I6: ='Model 2 Bos'!C145 -> -0.20011942 | J6: =AVERAGE(B6:I6) -> -0.51104361 | K6: =IF(J6>0,"Undervalued","Overvalued") -> Overvalued
A7: Chicago | B7: ='Model 2 Chi'!C138 -> -0.60899413 | C7: ='Model 2 Chi'!C139 -> -0.65063342 | D7: ='Model 2 Chi'!C140 -> -0.30985111 | E7: ='Model 2 Chi'!C141 -> -0.18545534 | F7: ='Model 2 Chi'!C142 -> -0.22288025 | G7: ='Model 2 Chi'!C143 -> -0.051005611 | H7: ='Model 2 Chi'!C144 -> 0.02707289 | I7: ='Model 2 Chi'!C145 -> 0.0016366377 | J7: =AVERAGE(B7:I7) -> -0.25001379 | K7: =IF(J7>0,"Undervalued","Overvalued") -> Overvalued
A8: Dallas | B8: ='Model 2 DAL'!C138 -> -0.34779919 | C8: ='Model 2 DAL'!C139 -> -0.29434611 | D8: ='Model 2 DAL'!C140 -> -0.04246779 | E8: ='Model 2 DAL'!C141 -> 0.11680844 | F8: ='Model 2 DAL'!C142 -> 0.18230941 | G8: ='Model 2 DAL'!C143 -> -0.097568834 | H8: ='Model 2 DAL'!C144 -> -0.3153081 | I8: ='Model 2 DAL'!C145 -> -0.59534694 | J8: =AVERAGE(B8:I8) -> -0.17421489 | K8: =IF(J8>0,"Undervalued","Overvalued") -> Overvalued
A9: NewYork | B9: ='Model 2 NY'!C138 -> -0.61030356 | C9: ='Model 2 NY'!C139 -> -0.6624092 | D9: ='Model 2 NY'!C140 -> -0.34237174 | E9: ='Model 2 NY'!C141 -> -0.4363883 | F9: ='Model 2 NY'!C142 -> -0.44273864 | G9: ='Model 2 NY'!C143 -> -0.37479248 | H9: ='Model 2 NY'!C144 -> -0.21909914 | I9: ='Model 2 NY'!C145 -> -0.1803426 | J9: =AVERAGE(B9:I9) -> -0.40855571 | K9: =IF(J9>0,"Undervalued","Overvalued") -> Overvalued
A10: OrangeCounty | B10: ='Model 2 OC'!C138 -> -0.004068961 | C10: ='Model 2 OC'!C139 -> 0.13782392 | D10: ='Model 2 OC'!C140 -> 0.46593607 | E10: ='Model 2 OC'!C141 -> 0.60681494 | F10: ='Model 2 OC'!C142 -> 0.64788518 | G10: ='Model 2 OC'!C143 -> 0.29345739 | H10: ='Model 2 OC'!C144 -> 0.22354399 | I10: ='Model 2 OC'!C145 -> 0.15981101 | J10: =AVERAGE(B10:I10) -> 0.31640044 | K10: =IF(J10>0,"Undervalued","Overvalued") -> Undervalued
A11: SanDiego | B11: ='Model 2 SD'!C138 -> -0.016923132 | C11: ='Model 2 SD'!C139 -> 0.08435511 | D11: ='Model 2 SD'!C140 -> 0.07703298 | E11: ='Model 2 SD'!C141 -> -0.10249702 | F11: ='Model 2 SD'!C142 -> -0.13265371 | G11: ='Model 2 SD'!C143 -> -0.038651467 | H11: ='Model 2 SD'!C144 -> 0.12300636 | I11: ='Model 2 SD'!C145 -> 0.23751477 | J11: =AVERAGE(B11:I11) -> 0.028897986 | K11: =IF(J11>0,"Undervalued","Overvalued") -> Undervalued
A12: SanJose | B12: ='Model 2 San Jose'!C138 -> -0.44873293 | C12: ='Model 2 San Jose'!C139 -> -0.42272813 | D12: ='Model 2 San Jose'!C140 -> -0.2274963 | E12: ='Model 2 San Jose'!C141 -> -0.29670042 | F12: ='Model 2 San Jose'!C142 -> -0.23437735 | G12: ='Model 2 San Jose'!C143 -> -0.21567035 | H12: ='Model 2 San Jose'!C144 -> -0.23335292 | I12: ='Model 2 San Jose'!C145 -> -0.34336177 | J12: =AVERAGE(B12:I12) -> -0.30280252 | K12: =IF(J12>0,"Undervalued","Overvalued") -> Overvalued
A15: Market Ranking (Best to Worst Investment Opportunity)
A17: Rank | B17: City | C17: Avg Residual
A18: 1 | B18: OrangeCounty | C18: =J10 -> 0.31640044
A19: 2 | B19: SanDiego | C19: =J11 -> 0.028897986
A20: 3 | B20: Chicago | C20: =J7 -> -0.25001379
A21: 4 | B21: San Jose | C21: =J12 -> -0.30280252
A22: 5 | B22: NewYork | C22: =J9 -> -0.40855571
A23: 6 | B23: Dallas | C23: =J8 -> -0.17421489
A24: 7 | B24: Boston | C24: =J6 -> -0.51104361
A25: 8 | B25: Atlanta | C25: =J5 -> -0.67675382
